{
"meta":{"test_sets":[],"test_metrics":[],"learn_metrics":[{"best_value":"Min","name":"RMSE"}],"launch_mode":"Train","parameters":"","iteration_count":1000,"learn_sets":["learn"],"name":"experiment"},
"iterations":[
{"learn":[14.59871775],"iteration":0,"passed_time":0.1432641435,"remaining_time":143.1208794},
{"learn":[14.22518863],"iteration":1,"passed_time":0.1439777271,"remaining_time":71.84488584},
{"learn":[13.8866124],"iteration":2,"passed_time":0.1446032345,"remaining_time":48.05647492},
{"learn":[13.52356875],"iteration":3,"passed_time":0.1452610807,"remaining_time":36.17000909},
{"learn":[13.18870211],"iteration":4,"passed_time":0.145872629,"remaining_time":29.02865318},
{"learn":[12.9124226],"iteration":5,"passed_time":0.1465106624,"remaining_time":24.27193306},
{"learn":[12.60003351],"iteration":6,"passed_time":0.147119445,"remaining_time":20.86994412},
{"learn":[12.32990573],"iteration":7,"passed_time":0.1477222853,"remaining_time":18.31756338},
{"learn":[12.0660619],"iteration":8,"passed_time":0.1483167883,"remaining_time":16.33132636},
{"learn":[11.77309809],"iteration":9,"passed_time":0.1489440393,"remaining_time":14.74545989},
{"learn":[11.49227636],"iteration":10,"passed_time":0.1495495251,"remaining_time":13.44586184},
{"learn":[11.26264833],"iteration":11,"passed_time":0.1501802632,"remaining_time":12.36484167},
{"learn":[11.04260393],"iteration":12,"passed_time":0.1508197195,"remaining_time":11.45069716},
{"learn":[10.79916926],"iteration":13,"passed_time":0.1514406874,"remaining_time":10.66575127},
{"learn":[10.5541002],"iteration":14,"passed_time":0.1520736903,"remaining_time":9.986172327},
{"learn":[10.31918115],"iteration":15,"passed_time":0.1526730534,"remaining_time":9.389392782},
{"learn":[10.10004441],"iteration":16,"passed_time":0.1532699714,"remaining_time":8.862610699},
{"learn":[9.894556723],"iteration":17,"passed_time":0.1538355043,"remaining_time":8.392581402},
{"learn":[9.690174082],"iteration":18,"passed_time":0.1543956661,"remaining_time":7.971692024},
{"learn":[9.506034866],"iteration":19,"passed_time":0.1549512985,"remaining_time":7.592613627},
{"learn":[9.338524633],"iteration":20,"passed_time":0.1555304497,"remaining_time":7.250681441},
{"learn":[9.170203312],"iteration":21,"passed_time":0.1560729849,"remaining_time":6.938153603},
{"learn":[9.010299969],"iteration":22,"passed_time":0.1565977132,"remaining_time":6.651998515},
{"learn":[8.843866678],"iteration":23,"passed_time":0.1571117694,"remaining_time":6.389211956},
{"learn":[8.690548059],"iteration":24,"passed_time":0.1576116762,"remaining_time":6.146855373},
{"learn":[8.555307687],"iteration":25,"passed_time":0.1581141584,"remaining_time":5.923199626},
{"learn":[8.413851302],"iteration":26,"passed_time":0.1586099667,"remaining_time":5.715833245},
{"learn":[8.29256019],"iteration":27,"passed_time":0.1591166276,"remaining_time":5.523620071},
{"learn":[8.162193833],"iteration":28,"passed_time":0.1596126363,"remaining_time":5.344271374},
{"learn":[8.040736294],"iteration":29,"passed_time":0.1601161506,"remaining_time":5.177088869},
{"learn":[7.921220278],"iteration":30,"passed_time":0.1606194845,"remaining_time":5.02065421},
{"learn":[7.809589039],"iteration":31,"passed_time":0.1611204636,"remaining_time":4.873894023},
{"learn":[7.699675801],"iteration":32,"passed_time":0.1616366141,"remaining_time":4.736442601},
{"learn":[7.60645267],"iteration":33,"passed_time":0.1621462711,"remaining_time":4.606861703},
{"learn":[7.498880302],"iteration":34,"passed_time":0.1626552468,"remaining_time":4.484637518},
{"learn":[7.401158744],"iteration":35,"passed_time":0.1631657856,"remaining_time":4.369217149},
{"learn":[7.306431077],"iteration":36,"passed_time":0.163663558,"remaining_time":4.259675848},
{"learn":[7.223863468],"iteration":37,"passed_time":0.1641806004,"remaining_time":4.156361516},
{"learn":[7.143477682],"iteration":38,"passed_time":0.1646877222,"remaining_time":4.058074385},
{"learn":[7.062817131],"iteration":39,"passed_time":0.1651947338,"remaining_time":3.96467361},
{"learn":[6.990793435],"iteration":40,"passed_time":0.1657120868,"remaining_time":3.876046127},
{"learn":[6.931862224],"iteration":41,"passed_time":0.1662419758,"remaining_time":3.791900304},
{"learn":[6.858296558],"iteration":42,"passed_time":0.1667602106,"remaining_time":3.711384222},
{"learn":[6.786268161],"iteration":43,"passed_time":0.1672783753,"remaining_time":3.634502881},
{"learn":[6.717118549],"iteration":44,"passed_time":0.1677957884,"remaining_time":3.56099951},
{"learn":[6.652948106],"iteration":45,"passed_time":0.1683117886,"remaining_time":3.490640138},
{"learn":[6.589686076],"iteration":46,"passed_time":0.1688182891,"remaining_time":3.423060203},
{"learn":[6.531283097],"iteration":47,"passed_time":0.1693351211,"remaining_time":3.358479901},
{"learn":[6.471368031],"iteration":48,"passed_time":0.1698512114,"remaining_time":3.296500043},
{"learn":[6.416481395],"iteration":49,"passed_time":0.1703622714,"remaining_time":3.236883157},
{"learn":[6.369870822],"iteration":50,"passed_time":0.1708706558,"remaining_time":3.17953436},
{"learn":[6.325678067],"iteration":51,"passed_time":0.1713759438,"remaining_time":3.124315283},
{"learn":[6.275766122],"iteration":52,"passed_time":0.1718831457,"remaining_time":3.071195076},
{"learn":[6.224773967],"iteration":53,"passed_time":0.1723892254,"remaining_time":3.020003837},
{"learn":[6.182249254],"iteration":54,"passed_time":0.1729040932,"remaining_time":2.970806693},
{"learn":[6.139904173],"iteration":55,"passed_time":0.1734215865,"remaining_time":2.923392459},
{"learn":[6.100525536],"iteration":56,"passed_time":0.1739140679,"remaining_time":2.877209931},
{"learn":[6.062568564],"iteration":57,"passed_time":0.1744072508,"remaining_time":2.832614315},
{"learn":[6.030559288],"iteration":58,"passed_time":0.1749204653,"remaining_time":2.789833183},
{"learn":[5.997931376],"iteration":59,"passed_time":0.1754132172,"remaining_time":2.748140403},
{"learn":[5.964103835],"iteration":60,"passed_time":0.1759071717,"remaining_time":2.707816955},
{"learn":[5.933729724],"iteration":61,"passed_time":0.1764173799,"remaining_time":2.669024231},
{"learn":[5.901932711],"iteration":62,"passed_time":0.1769390819,"remaining_time":2.631617774},
{"learn":[5.873727795],"iteration":63,"passed_time":0.1774510037,"remaining_time":2.595220929},
{"learn":[5.846485734],"iteration":64,"passed_time":0.1779686974,"remaining_time":2.560011262},
{"learn":[5.820630862],"iteration":65,"passed_time":0.1784968127,"remaining_time":2.52600035},
{"learn":[5.793646238],"iteration":66,"passed_time":0.1790086443,"remaining_time":2.492762166},
{"learn":[5.765388646],"iteration":67,"passed_time":0.1795234019,"remaining_time":2.460526626},
{"learn":[5.747073912],"iteration":68,"passed_time":0.1800662177,"remaining_time":2.429589112},
{"learn":[5.722315217],"iteration":69,"passed_time":0.180568259,"remaining_time":2.398978298},
{"learn":[5.699970599],"iteration":70,"passed_time":0.1810810024,"remaining_time":2.369355651},
{"learn":[5.682732647],"iteration":71,"passed_time":0.1816158216,"remaining_time":2.340826146},
{"learn":[5.663525791],"iteration":72,"passed_time":0.1821461315,"remaining_time":2.313006355},
{"learn":[5.642381613],"iteration":73,"passed_time":0.1826795779,"remaining_time":2.285963367},
{"learn":[5.621404779],"iteration":74,"passed_time":0.1831978629,"remaining_time":2.259440309},
{"learn":[5.602460129],"iteration":75,"passed_time":0.1837343055,"remaining_time":2.233822345},
{"learn":[5.587337574],"iteration":76,"passed_time":0.1842351242,"remaining_time":2.208428826},
{"learn":[5.572393026],"iteration":77,"passed_time":0.1847327563,"remaining_time":2.183635914},
{"learn":[5.558425806],"iteration":78,"passed_time":0.1852432651,"remaining_time":2.159608192},
{"learn":[5.541518902],"iteration":79,"passed_time":0.1857572511,"remaining_time":2.136208388},
{"learn":[5.526157283],"iteration":80,"passed_time":0.186262489,"remaining_time":2.113274412},
{"learn":[5.511746977],"iteration":81,"passed_time":0.1867789902,"remaining_time":2.091013574},
{"learn":[5.504975022],"iteration":82,"passed_time":0.187056115,"remaining_time":2.066632018},
{"learn":[5.493980522],"iteration":83,"passed_time":0.1875825569,"remaining_time":2.04554312},
{"learn":[5.480745463],"iteration":84,"passed_time":0.1880945087,"remaining_time":2.024782064},
{"learn":[5.464052013],"iteration":85,"passed_time":0.1886229246,"remaining_time":2.004666897},
{"learn":[5.449143727],"iteration":86,"passed_time":0.1891685062,"remaining_time":1.985182139},
{"learn":[5.438255432],"iteration":87,"passed_time":0.1896812697,"remaining_time":1.965787704},
{"learn":[5.425927931],"iteration":88,"passed_time":0.1901946144,"remaining_time":1.946823524},
{"learn":[5.412331217],"iteration":89,"passed_time":0.1907143623,"remaining_time":1.928334108},
{"learn":[5.400691499],"iteration":90,"passed_time":0.1912285788,"remaining_time":1.910184375},
{"learn":[5.391618744],"iteration":91,"passed_time":0.1917369131,"remaining_time":1.892359969},
{"learn":[5.380766572],"iteration":92,"passed_time":0.1922459489,"remaining_time":1.874914792},
{"learn":[5.372207183],"iteration":93,"passed_time":0.1927814896,"remaining_time":1.858085421},
{"learn":[5.362918837],"iteration":94,"passed_time":0.1932915074,"remaining_time":1.841355939},
{"learn":[5.348292324],"iteration":95,"passed_time":0.19380382,"remaining_time":1.824985971},
{"learn":[5.339772295],"iteration":96,"passed_time":0.1943102904,"remaining_time":1.80888858},
{"learn":[5.331515983],"iteration":97,"passed_time":0.1948306497,"remaining_time":1.793237204},
{"learn":[5.323861644],"iteration":98,"passed_time":0.1953280813,"remaining_time":1.777682841},
{"learn":[5.313277281],"iteration":99,"passed_time":0.1958409651,"remaining_time":1.762568686},
{"learn":[5.30685627],"iteration":100,"passed_time":0.1963745317,"remaining_time":1.747927762},
{"learn":[5.29652059],"iteration":101,"passed_time":0.1969257249,"remaining_time":1.733718637},
{"learn":[5.288350766],"iteration":102,"passed_time":0.1974400116,"remaining_time":1.719453305},
{"learn":[5.27993346],"iteration":103,"passed_time":0.1979771556,"remaining_time":1.705649341},
{"learn":[5.271789139],"iteration":104,"passed_time":0.1984840369,"remaining_time":1.691840124},
{"learn":[5.262684686],"iteration":105,"passed_time":0.1989909683,"remaining_time":1.678282318},
{"learn":[5.251619772],"iteration":106,"passed_time":0.1995143137,"remaining_time":1.665105441},
{"learn":[5.241012171],"iteration":107,"passed_time":0.2000459063,"remaining_time":1.652231004},
{"learn":[5.232684032],"iteration":108,"passed_time":0.2005620367,"remaining_time":1.639456649},
{"learn":[5.224267141],"iteration":109,"passed_time":0.2010771251,"remaining_time":1.626896739},
{"learn":[5.216324968],"iteration":110,"passed_time":0.2015898585,"remaining_time":1.614534993},
{"learn":[5.211102527],"iteration":111,"passed_time":0.202094936,"remaining_time":1.602324136},
{"learn":[5.206364257],"iteration":112,"passed_time":0.2025888003,"remaining_time":1.590232441},
{"learn":[5.196937641],"iteration":113,"passed_time":0.2031016139,"remaining_time":1.578491491},
{"learn":[5.190746047],"iteration":114,"passed_time":0.2036133252,"remaining_time":1.566937329},
{"learn":[5.181885213],"iteration":115,"passed_time":0.2041182124,"remaining_time":1.555521549},
{"learn":[5.178293568],"iteration":116,"passed_time":0.204532221,"remaining_time":1.54360642},
{"learn":[5.170991438],"iteration":117,"passed_time":0.2050557569,"remaining_time":1.532704895},
{"learn":[5.166257212],"iteration":118,"passed_time":0.2055724886,"remaining_time":1.521927416},
{"learn":[5.161421246],"iteration":119,"passed_time":0.2060691787,"remaining_time":1.511173977},
{"learn":[5.158223542],"iteration":120,"passed_time":0.2065898186,"remaining_time":1.500764054},
{"learn":[5.15470988],"iteration":121,"passed_time":0.2070155716,"remaining_time":1.489833376},
{"learn":[5.146388143],"iteration":122,"passed_time":0.2075404101,"remaining_time":1.479779997},
{"learn":[5.139529364],"iteration":123,"passed_time":0.2080494659,"remaining_time":1.469768808},
{"learn":[5.134276023],"iteration":124,"passed_time":0.2085646544,"remaining_time":1.459952581},
{"learn":[5.128536065],"iteration":125,"passed_time":0.2090866872,"remaining_time":1.450331465},
{"learn":[5.123300353],"iteration":126,"passed_time":0.2094985514,"remaining_time":1.440096341},
{"learn":[5.116200518],"iteration":127,"passed_time":0.2100376294,"remaining_time":1.430881351},
{"learn":[5.108728704],"iteration":128,"passed_time":0.2105898548,"remaining_time":1.42188964},
{"learn":[5.104075866],"iteration":129,"passed_time":0.2111003335,"remaining_time":1.412748386},
{"learn":[5.100317606],"iteration":130,"passed_time":0.2116066737,"remaining_time":1.403711446},
{"learn":[5.095814182],"iteration":131,"passed_time":0.2121223633,"remaining_time":1.394865237},
{"learn":[5.092146915],"iteration":132,"passed_time":0.2126257473,"remaining_time":1.386064082},
{"learn":[5.085258329],"iteration":133,"passed_time":0.2131375287,"remaining_time":1.377441044},
{"learn":[5.079219421],"iteration":134,"passed_time":0.2136523565,"remaining_time":1.368957692},
{"learn":[5.076476829],"iteration":135,"passed_time":0.2141527644,"remaining_time":1.360499915},
{"learn":[5.072133867],"iteration":136,"passed_time":0.2146595956,"remaining_time":1.352198766},
{"learn":[5.067031564],"iteration":137,"passed_time":0.2151702847,"remaining_time":1.344034677},
{"learn":[5.061358312],"iteration":138,"passed_time":0.215691606,"remaining_time":1.336046567},
{"learn":[5.056759124],"iteration":139,"passed_time":0.2161907913,"remaining_time":1.328029147},
{"learn":[5.050254],"iteration":140,"passed_time":0.2167058496,"remaining_time":1.320215069},
{"learn":[5.048376474],"iteration":141,"passed_time":0.2170642028,"remaining_time":1.311556944},
{"learn":[5.042603751],"iteration":142,"passed_time":0.2175719359,"remaining_time":1.303910133},
{"learn":[5.037477349],"iteration":143,"passed_time":0.218092265,"remaining_time":1.296437353},
{"learn":[5.03230489],"iteration":144,"passed_time":0.2186058302,"remaining_time":1.289020585},
{"learn":[5.025976187],"iteration":145,"passed_time":0.2191207281,"remaining_time":1.281706177},
{"learn":[5.01952451],"iteration":146,"passed_time":0.2196266274,"remaining_time":1.274432062},
{"learn":[5.017569424],"iteration":147,"passed_time":0.2201113126,"remaining_time":1.267127286},
{"learn":[5.008962367],"iteration":148,"passed_time":0.2206280744,"remaining_time":1.260097257},
{"learn":[5.003880266],"iteration":149,"passed_time":0.2211675633,"remaining_time":1.253282859},
{"learn":[4.996387564],"iteration":150,"passed_time":0.2216845355,"remaining_time":1.246424971},
{"learn":[4.993361683],"iteration":151,"passed_time":0.222199223,"remaining_time":1.23963777},
{"learn":[4.99005752],"iteration":152,"passed_time":0.2227178687,"remaining_time":1.232954476},
{"learn":[4.986908764],"iteration":153,"passed_time":0.2232206815,"remaining_time":1.226264264},
{"learn":[4.985207175],"iteration":154,"passed_time":0.2237140648,"remaining_time":1.219602483},
{"learn":[4.979003494],"iteration":155,"passed_time":0.2242655186,"remaining_time":1.213333959},
{"learn":[4.973142217],"iteration":156,"passed_time":0.2247886436,"remaining_time":1.206986156},
{"learn":[4.967056696],"iteration":157,"passed_time":0.2253015774,"remaining_time":1.200657773},
{"learn":[4.961460696],"iteration":158,"passed_time":0.2258155033,"remaining_time":1.194407788},
{"learn":[4.954240363],"iteration":159,"passed_time":0.2263403218,"remaining_time":1.188286689},
{"learn":[4.952320707],"iteration":160,"passed_time":0.2266795453,"remaining_time":1.181267941},
{"learn":[4.948337777],"iteration":161,"passed_time":0.2271981409,"remaining_time":1.175259519},
{"learn":[4.943228639],"iteration":162,"passed_time":0.2276959434,"remaining_time":1.169211685},
{"learn":[4.938545759],"iteration":163,"passed_time":0.2282278766,"remaining_time":1.163405518},
{"learn":[4.935330572],"iteration":164,"passed_time":0.228733826,"remaining_time":1.157531786},
{"learn":[4.932051543],"iteration":165,"passed_time":0.2292493953,"remaining_time":1.151771058},
{"learn":[4.928964153],"iteration":166,"passed_time":0.2297520178,"remaining_time":1.146008568},
{"learn":[4.922860227],"iteration":167,"passed_time":0.2302542795,"remaining_time":1.140306908},
{"learn":[4.917668772],"iteration":168,"passed_time":0.2307598681,"remaining_time":1.134683138},
{"learn":[4.910365386],"iteration":169,"passed_time":0.2312997378,"remaining_time":1.129286955},
{"learn":[4.906457206],"iteration":170,"passed_time":0.2318232436,"remaining_time":1.123868239},
{"learn":[4.901996508],"iteration":171,"passed_time":0.2323361473,"remaining_time":1.118455407},
{"learn":[4.896816173],"iteration":172,"passed_time":0.2328477284,"remaining_time":1.113092898},
{"learn":[4.891123132],"iteration":173,"passed_time":0.2333768257,"remaining_time":1.107869299},
{"learn":[4.887630202],"iteration":174,"passed_time":0.2338775843,"remaining_time":1.102565755},
{"learn":[4.885259712],"iteration":175,"passed_time":0.2343995469,"remaining_time":1.09741606},
{"learn":[4.880659728],"iteration":176,"passed_time":0.2349162586,"remaining_time":1.092294242},
{"learn":[4.877299723],"iteration":177,"passed_time":0.2354423697,"remaining_time":1.087267573},
{"learn":[4.874038772],"iteration":178,"passed_time":0.2359569871,"remaining_time":1.082238471},
{"learn":[4.86943698],"iteration":179,"passed_time":0.2364560121,"remaining_time":1.077188499},
{"learn":[4.861268711],"iteration":180,"passed_time":0.2369777542,"remaining_time":1.072291606},
{"learn":[4.858673056],"iteration":181,"passed_time":0.2374969711,"remaining_time":1.067431441},
{"learn":[4.854036207],"iteration":182,"passed_time":0.2379939318,"remaining_time":1.062519357},
{"learn":[4.85130244],"iteration":183,"passed_time":0.2385455058,"remaining_time":1.05789746},
{"learn":[4.847510084],"iteration":184,"passed_time":0.2390979215,"remaining_time":1.053323276},
{"learn":[4.845691673],"iteration":185,"passed_time":0.2396216678,"remaining_time":1.048666869},
{"learn":[4.842058646],"iteration":186,"passed_time":0.2401361548,"remaining_time":1.044014406},
{"learn":[4.838623675],"iteration":187,"passed_time":0.2406699419,"remaining_time":1.039489324},
{"learn":[4.834602161],"iteration":188,"passed_time":0.2411918844,"remaining_time":1.034955652},
{"learn":[4.830858976],"iteration":189,"passed_time":0.2417029945,"remaining_time":1.030418029},
{"learn":[4.827590511],"iteration":190,"passed_time":0.2422266606,"remaining_time":1.025975751},
{"learn":[4.822246226],"iteration":191,"passed_time":0.2427450457,"remaining_time":1.021552068},
{"learn":[4.816686395],"iteration":192,"passed_time":0.2432559554,"remaining_time":1.017137596},
{"learn":[4.814797121],"iteration":193,"passed_time":0.2437645903,"remaining_time":1.012753916},
{"learn":[4.811639392],"iteration":194,"passed_time":0.2442906213,"remaining_time":1.008481796},
{"learn":[4.804813432],"iteration":195,"passed_time":0.2448283366,"remaining_time":1.00429583},
{"learn":[4.80251613],"iteration":196,"passed_time":0.2453321415,"remaining_time":1.000008678},
{"learn":[4.800087884],"iteration":197,"passed_time":0.2458639044,"remaining_time":0.9958729864},
{"learn":[4.794773135],"iteration":198,"passed_time":0.2463854561,"remaining_time":0.9917324137},
{"learn":[4.791664833],"iteration":199,"passed_time":0.2468895516,"remaining_time":0.9875582064},
{"learn":[4.785989873],"iteration":200,"passed_time":0.2474075459,"remaining_time":0.9834757671},
{"learn":[4.782387142],"iteration":201,"passed_time":0.2479377155,"remaining_time":0.9794767177},
{"learn":[4.778623704],"iteration":202,"passed_time":0.2484552289,"remaining_time":0.9754621547},
{"learn":[4.775772178],"iteration":203,"passed_time":0.2489517386,"remaining_time":0.9713999213},
{"learn":[4.77023101],"iteration":204,"passed_time":0.2494887524,"remaining_time":0.9675295521},
{"learn":[4.764496689],"iteration":205,"passed_time":0.2499984796,"remaining_time":0.9635863729},
{"learn":[4.763138716],"iteration":206,"passed_time":0.2505039379,"remaining_time":0.9596600135},
{"learn":[4.758053283],"iteration":207,"passed_time":0.2510288967,"remaining_time":0.9558407991},
{"learn":[4.755063788],"iteration":208,"passed_time":0.2515407183,"remaining_time":0.9520033883},
{"learn":[4.752465267],"iteration":209,"passed_time":0.2520646148,"remaining_time":0.9482430749},
{"learn":[4.748067377],"iteration":210,"passed_time":0.2526005564,"remaining_time":0.9445584787},
{"learn":[4.744163298],"iteration":211,"passed_time":0.2531343836,"remaining_time":0.9408957277},
{"learn":[4.736670896],"iteration":212,"passed_time":0.2536655352,"remaining_time":0.9372524705},
{"learn":[4.73349255],"iteration":213,"passed_time":0.2541857041,"remaining_time":0.9335979598},
{"learn":[4.731864595],"iteration":214,"passed_time":0.2546965536,"remaining_time":0.9299385793},
{"learn":[4.728398311],"iteration":215,"passed_time":0.2552219433,"remaining_time":0.9263611274},
{"learn":[4.723865975],"iteration":216,"passed_time":0.2557428035,"remaining_time":0.9227954616},
{"learn":[4.723483365],"iteration":217,"passed_time":0.2562257652,"remaining_time":0.9191217816},
{"learn":[4.72095416],"iteration":218,"passed_time":0.2567412343,"remaining_time":0.9155931689},
{"learn":[4.716173382],"iteration":219,"passed_time":0.2572410309,"remaining_time":0.9120363823},
{"learn":[4.710563974],"iteration":220,"passed_time":0.2577591956,"remaining_time":0.9085720062},
{"learn":[4.707160263],"iteration":221,"passed_time":0.2582871205,"remaining_time":0.9051683774},
{"learn":[4.70408351],"iteration":222,"passed_time":0.2588074998,"remaining_time":0.9017642483},
{"learn":[4.702501831],"iteration":223,"passed_time":0.2593332402,"remaining_time":0.8984044393},
{"learn":[4.700269738],"iteration":224,"passed_time":0.2598282369,"remaining_time":0.894963927},
{"learn":[4.695346302],"iteration":225,"passed_time":0.2603635972,"remaining_time":0.8916877179},
{"learn":[4.689769299],"iteration":226,"passed_time":0.2608925343,"remaining_time":0.888413784},
{"learn":[4.687919514],"iteration":227,"passed_time":0.2613984636,"remaining_time":0.8850860258},
{"learn":[4.682982074],"iteration":228,"passed_time":0.2619238232,"remaining_time":0.8818483304},
{"learn":[4.679578702],"iteration":229,"passed_time":0.2624281492,"remaining_time":0.8785638037},
{"learn":[4.675751423],"iteration":230,"passed_time":0.2629379565,"remaining_time":0.8753215955},
{"learn":[4.672710726],"iteration":231,"passed_time":0.2634606406,"remaining_time":0.8721455689},
{"learn":[4.6690533],"iteration":232,"passed_time":0.2639860904,"remaining_time":0.869001422},
{"learn":[4.667595702],"iteration":233,"passed_time":0.2644905366,"remaining_time":0.865810902},
{"learn":[4.664241291],"iteration":234,"passed_time":0.265001817,"remaining_time":0.8626654895},
{"learn":[4.662246999],"iteration":235,"passed_time":0.2655195208,"remaining_time":0.8595631944},
{"learn":[4.658668443],"iteration":236,"passed_time":0.2660221132,"remaining_time":0.8564340606},
{"learn":[4.658017572],"iteration":237,"passed_time":0.2666066856,"remaining_time":0.8535894724},
{"learn":[4.657656705],"iteration":238,"passed_time":0.2671012814,"remaining_time":0.8504773019},
{"learn":[4.653242871],"iteration":239,"passed_time":0.2676212999,"remaining_time":0.8474674498},
{"learn":[4.6507302],"iteration":240,"passed_time":0.2681360475,"remaining_time":0.8444616601},
{"learn":[4.647671336],"iteration":241,"passed_time":0.2686497329,"remaining_time":0.8414731305},
{"learn":[4.645506007],"iteration":242,"passed_time":0.2691679678,"remaining_time":0.8385191424},
{"learn":[4.641297906],"iteration":243,"passed_time":0.2696968948,"remaining_time":0.8356182478},
{"learn":[4.63798107],"iteration":244,"passed_time":0.270218176,"remaining_time":0.8327131545},
{"learn":[4.635062318],"iteration":245,"passed_time":0.2707310898,"remaining_time":0.8298017954},
{"learn":[4.631606017],"iteration":246,"passed_time":0.2712419693,"remaining_time":0.8269036555},
{"learn":[4.630215494],"iteration":247,"passed_time":0.2717764479,"remaining_time":0.8240963258},
{"learn":[4.62729814],"iteration":248,"passed_time":0.2723089022,"remaining_time":0.8213011468},
{"learn":[4.624691756],"iteration":249,"passed_time":0.2728221968,"remaining_time":0.8184665903},
{"learn":[4.621840053],"iteration":250,"passed_time":0.2733421652,"remaining_time":0.8156704452},
{"learn":[4.619602091],"iteration":251,"passed_time":0.2738421622,"remaining_time":0.8128330847},
{"learn":[4.613584029],"iteration":252,"passed_time":0.2743481717,"remaining_time":0.8100319536},
{"learn":[4.6119388],"iteration":253,"passed_time":0.2748521971,"remaining_time":0.807243067},
{"learn":[4.60870702],"iteration":254,"passed_time":0.2753738189,"remaining_time":0.8045235102},
{"learn":[4.604771557],"iteration":255,"passed_time":0.2758752589,"remaining_time":0.8017624713},
{"learn":[4.604231277],"iteration":256,"passed_time":0.2764237165,"remaining_time":0.7991549468},
{"learn":[4.600750354],"iteration":257,"passed_time":0.276953395,"remaining_time":0.7965093764},
{"learn":[4.596488253],"iteration":258,"passed_time":0.277468784,"remaining_time":0.7938392622},
{"learn":[4.59470784],"iteration":259,"passed_time":0.2780012283,"remaining_time":0.7912342651},
{"learn":[4.588818005],"iteration":260,"passed_time":0.2785212769,"remaining_time":0.7886100521},
{"learn":[4.585054174],"iteration":261,"passed_time":0.2790563667,"remaining_time":0.7860442694},
{"learn":[4.581471435],"iteration":262,"passed_time":0.2795647611,"remaining_time":0.7834191214},
{"learn":[4.577555199],"iteration":263,"passed_time":0.2800879562,"remaining_time":0.7808512719},
{"learn":[4.57457145],"iteration":264,"passed_time":0.2805952884,"remaining_time":0.7782548566},
{"learn":[4.573029224],"iteration":265,"passed_time":0.2811024102,"remaining_time":0.7756735681},
{"learn":[4.571326203],"iteration":266,"passed_time":0.2816349447,"remaining_time":0.7731775823},
{"learn":[4.571019224],"iteration":267,"passed_time":0.2821305827,"remaining_time":0.7705954721},
{"learn":[4.565766631],"iteration":268,"passed_time":0.2826400694,"remaining_time":0.7680665082},
{"learn":[4.563383471],"iteration":269,"passed_time":0.2831737963,"remaining_time":0.765618042},
{"learn":[4.558165805],"iteration":270,"passed_time":0.2836951477,"remaining_time":0.7631504156},
{"learn":[4.55629209],"iteration":271,"passed_time":0.2842049249,"remaining_time":0.7606661226},
{"learn":[4.549383848],"iteration":272,"passed_time":0.2847398744,"remaining_time":0.7582633287},
{"learn":[4.546227503],"iteration":273,"passed_time":0.2852631297,"remaining_time":0.7558431831},
{"learn":[4.540620977],"iteration":274,"passed_time":0.2857651008,"remaining_time":0.7533807203},
{"learn":[4.532898237],"iteration":275,"passed_time":0.2862860713,"remaining_time":0.750982303},
{"learn":[4.529757367],"iteration":276,"passed_time":0.2868306508,"remaining_time":0.7486590633},
{"learn":[4.52579294],"iteration":277,"passed_time":0.2873359889,"remaining_time":0.7462467049},
{"learn":[4.521572155],"iteration":278,"passed_time":0.2878607873,"remaining_time":0.743898307},
{"learn":[4.518818099],"iteration":279,"passed_time":0.2883746731,"remaining_time":0.7415348738},
{"learn":[4.514012334],"iteration":280,"passed_time":0.2889080694,"remaining_time":0.7392345264},
{"learn":[4.508331416],"iteration":281,"passed_time":0.289419921,"remaining_time":0.7368918557},
{"learn":[4.506038537],"iteration":282,"passed_time":0.2899215214,"remaining_time":0.7345361513},
{"learn":[4.505805643],"iteration":283,"passed_time":0.290430517,"remaining_time":0.7322121486},
{"learn":[4.501550352],"iteration":284,"passed_time":0.2909421883,"remaining_time":0.7299075951},
{"learn":[4.494692643],"iteration":285,"passed_time":0.291465183,"remaining_time":0.7276438484},
{"learn":[4.489330245],"iteration":286,"passed_time":0.2919704108,"remaining_time":0.7253480938},
{"learn":[4.484826955],"iteration":287,"passed_time":0.2924933354,"remaining_time":0.7231085236},
{"learn":[4.478285428],"iteration":288,"passed_time":0.2930064496,"remaining_time":0.7208566978},
{"learn":[4.475311671],"iteration":289,"passed_time":0.293516778,"remaining_time":0.7186100428},
{"learn":[4.471581298],"iteration":290,"passed_time":0.2940407047,"remaining_time":0.7164084523},
{"learn":[4.469164956],"iteration":291,"passed_time":0.2945493396,"remaining_time":0.7141812755},
{"learn":[4.462068024],"iteration":292,"passed_time":0.2950984284,"remaining_time":0.7120634434},
{"learn":[4.458540976],"iteration":293,"passed_time":0.2956275258,"remaining_time":0.7099082763},
{"learn":[4.455757458],"iteration":294,"passed_time":0.2961498491,"remaining_time":0.7077479445},
{"learn":[4.453027414],"iteration":295,"passed_time":0.2966798283,"remaining_time":0.705616889},
{"learn":[4.450659338],"iteration":296,"passed_time":0.2972051178,"remaining_time":0.7034855145},
{"learn":[4.444696901],"iteration":297,"passed_time":0.2977429332,"remaining_time":0.7013944266},
{"learn":[4.442052813],"iteration":298,"passed_time":0.298277542,"remaining_time":0.6993062106},
{"learn":[4.440036756],"iteration":299,"passed_time":0.2987846237,"remaining_time":0.6971641221},
{"learn":[4.435017051],"iteration":300,"passed_time":0.2993149236,"remaining_time":0.6950868159},
{"learn":[4.429962125],"iteration":301,"passed_time":0.299824771,"remaining_time":0.6929724841},
{"learn":[4.427666256],"iteration":302,"passed_time":0.3003419437,"remaining_time":0.6908855932},
{"learn":[4.425030004],"iteration":303,"passed_time":0.300855098,"remaining_time":0.6887998296},
{"learn":[4.422588771],"iteration":304,"passed_time":0.3013735032,"remaining_time":0.6867363433},
{"learn":[4.418936667],"iteration":305,"passed_time":0.3018925998,"remaining_time":0.6846845237},
{"learn":[4.416887976],"iteration":306,"passed_time":0.3023887188,"remaining_time":0.6825908212},
{"learn":[4.413773354],"iteration":307,"passed_time":0.3029127857,"remaining_time":0.6805702847},
{"learn":[4.411129391],"iteration":308,"passed_time":0.3034669851,"remaining_time":0.6786268178},
{"learn":[4.40850819],"iteration":309,"passed_time":0.30399006,"remaining_time":0.6766230368},
{"learn":[4.404880292],"iteration":310,"passed_time":0.3044999175,"remaining_time":0.6745994956},
{"learn":[4.404593827],"iteration":311,"passed_time":0.3049864666,"remaining_time":0.6725342596},
{"learn":[4.402139942],"iteration":312,"passed_time":0.3054914138,"remaining_time":0.670519493},
{"learn":[4.400284725],"iteration":313,"passed_time":0.3060045581,"remaining_time":0.6685322512},
{"learn":[4.395805521],"iteration":314,"passed_time":0.3065409306,"remaining_time":0.6666048808},
{"learn":[4.392838833],"iteration":315,"passed_time":0.3070527822,"remaining_time":0.6646332374},
{"learn":[4.389213061],"iteration":316,"passed_time":0.307566197,"remaining_time":0.6626741721},
{"learn":[4.3861981],"iteration":317,"passed_time":0.3080885704,"remaining_time":0.6607434121},
{"learn":[4.385054234],"iteration":318,"passed_time":0.3085923854,"remaining_time":0.6587818634},
{"learn":[4.379364607],"iteration":319,"passed_time":0.3091349507,"remaining_time":0.6569117702},
{"learn":[4.378387619],"iteration":320,"passed_time":0.3096767644,"remaining_time":0.6550483584},
{"learn":[4.375816727],"iteration":321,"passed_time":0.3102338699,"remaining_time":0.6532253533},
{"learn":[4.374600202],"iteration":322,"passed_time":0.3107769963,"remaining_time":0.651380887},
{"learn":[4.37098897],"iteration":323,"passed_time":0.3113281795,"remaining_time":0.6495612634},
{"learn":[4.367418484],"iteration":324,"passed_time":0.3119219009,"remaining_time":0.6478377942},
{"learn":[4.363584638],"iteration":325,"passed_time":0.3124853796,"remaining_time":0.6460587295},
{"learn":[4.360770706],"iteration":326,"passed_time":0.3130589091,"remaining_time":0.6443077854},
{"learn":[4.358675808],"iteration":327,"passed_time":0.313607557,"remaining_time":0.6425130436},
{"learn":[4.354228195],"iteration":328,"passed_time":0.3141382777,"remaining_time":0.6406893142},
{"learn":[4.353773425],"iteration":329,"passed_time":0.3146418421,"remaining_time":0.6388182856},
{"learn":[4.351648009],"iteration":330,"passed_time":0.3151582231,"remaining_time":0.6369814238},
{"learn":[4.348209927],"iteration":331,"passed_time":0.3156758968,"remaining_time":0.6351551177},
{"learn":[4.345852733],"iteration":332,"passed_time":0.3161878186,"remaining_time":0.6333251501},
{"learn":[4.34237339],"iteration":333,"passed_time":0.316707787,"remaining_time":0.6315191202},
{"learn":[4.340814362],"iteration":334,"passed_time":0.3172282264,"remaining_time":0.6297217031},
{"learn":[4.339707068],"iteration":335,"passed_time":0.31774585,"remaining_time":0.6279263226},
{"learn":[4.335430786],"iteration":336,"passed_time":0.3182695461,"remaining_time":0.6261504721},
{"learn":[4.33521887],"iteration":337,"passed_time":0.3187713469,"remaining_time":0.6243391469},
{"learn":[4.328507238],"iteration":338,"passed_time":0.3193345049,"remaining_time":0.6226551851},
{"learn":[4.326140732],"iteration":339,"passed_time":0.3198612674,"remaining_time":0.6209071662},
{"learn":[4.323785636],"iteration":340,"passed_time":0.3203727583,"remaining_time":0.6191367968},
{"learn":[4.320632534],"iteration":341,"passed_time":0.3208889088,"remaining_time":0.6173827543},
{"learn":[4.31973724],"iteration":342,"passed_time":0.3213846269,"remaining_time":0.6155967927},
{"learn":[4.318000924],"iteration":343,"passed_time":0.3219130529,"remaining_time":0.6138807055},
{"learn":[4.312713628],"iteration":344,"passed_time":0.3224810409,"remaining_time":0.6122466139},
{"learn":[4.308220789],"iteration":345,"passed_time":0.3230091562,"remaining_time":0.6105433184},
{"learn":[4.305890947],"iteration":346,"passed_time":0.3235282629,"remaining_time":0.6088298434},
{"learn":[4.305137856],"iteration":347,"passed_time":0.3240389922,"remaining_time":0.607107537},
{"learn":[4.304787172],"iteration":348,"passed_time":0.324537476,"remaining_time":0.6053693321},
{"learn":[4.30350134],"iteration":349,"passed_time":0.3250355491,"remaining_time":0.6036374482},
{"learn":[4.30293809],"iteration":350,"passed_time":0.3255381815,"remaining_time":0.6019210251},
{"learn":[4.299548459],"iteration":351,"passed_time":0.3260580498,"remaining_time":0.600243228},
{"learn":[4.294768408],"iteration":352,"passed_time":0.3265773368,"remaining_time":0.598570926},
{"learn":[4.294581479],"iteration":353,"passed_time":0.3270675635,"remaining_time":0.5968521074},
{"learn":[4.292551604],"iteration":354,"passed_time":0.3275873516,"remaining_time":0.5951939205},
{"learn":[4.288628894],"iteration":355,"passed_time":0.3281076206,"remaining_time":0.5935429991},
{"learn":[4.287802767],"iteration":356,"passed_time":0.3286133996,"remaining_time":0.5918723136},
{"learn":[4.284566905],"iteration":357,"passed_time":0.3291390899,"remaining_time":0.5902438428},
{"learn":[4.27890232],"iteration":358,"passed_time":0.3296847717,"remaining_time":0.5886572107},
{"learn":[4.276938023],"iteration":359,"passed_time":0.3302109129,"remaining_time":0.587041623},
{"learn":[4.273425094],"iteration":360,"passed_time":0.3307376053,"remaining_time":0.5854330465},
{"learn":[4.269726505],"iteration":361,"passed_time":0.3312679853,"remaining_time":0.5838369465},
{"learn":[4.265565857],"iteration":362,"passed_time":0.3317848273,"remaining_time":0.5822229614},
{"learn":[4.262117173],"iteration":363,"passed_time":0.3323087639,"remaining_time":0.5806274007},
{"learn":[4.259185148],"iteration":364,"passed_time":0.3328375006,"remaining_time":0.5790460626},
{"learn":[4.257668507],"iteration":365,"passed_time":0.3333545329,"remaining_time":0.5774502018},
{"learn":[4.253432436],"iteration":366,"passed_time":0.3338688596,"remaining_time":0.5758555535},
{"learn":[4.250216667],"iteration":367,"passed_time":0.3343944297,"remaining_time":0.5742860858},
{"learn":[4.24514828],"iteration":368,"passed_time":0.3349463143,"remaining_time":0.5727672746},
{"learn":[4.244015772],"iteration":369,"passed_time":0.3354595688,"remaining_time":0.5711879145},
{"learn":[4.240329192],"iteration":370,"passed_time":0.3360274767,"remaining_time":0.5697069618},
{"learn":[4.236718014],"iteration":371,"passed_time":0.3366221501,"remaining_time":0.5682761028},
{"learn":[4.233495944],"iteration":372,"passed_time":0.337181921,"remaining_time":0.5667910576},
{"learn":[4.230357491],"iteration":373,"passed_time":0.3377327334,"remaining_time":0.5652959656},
{"learn":[4.227381215],"iteration":374,"passed_time":0.3382929053,"remaining_time":0.5638215088},
{"learn":[4.226169067],"iteration":375,"passed_time":0.3388138457,"remaining_time":0.5622868078},
{"learn":[4.225963861],"iteration":376,"passed_time":0.3393181316,"remaining_time":0.5607299629},
{"learn":[4.224346548],"iteration":377,"passed_time":0.3398350738,"remaining_time":0.5591995129},
{"learn":[4.222595381],"iteration":378,"passed_time":0.3403549019,"remaining_time":0.5576791401},
{"learn":[4.219700938],"iteration":379,"passed_time":0.3408710324,"remaining_time":0.5561580002},
{"learn":[4.216356207],"iteration":380,"passed_time":0.3413841165,"remaining_time":0.5546371867},
{"learn":[4.214326494],"iteration":381,"passed_time":0.3419071313,"remaining_time":0.553137715},
{"learn":[4.212901398],"iteration":382,"passed_time":0.3424205561,"remaining_time":0.5516278933},
{"learn":[4.211331091],"iteration":383,"passed_time":0.3429451241,"remaining_time":0.5501411366},
{"learn":[4.208624791],"iteration":384,"passed_time":0.3434664053,"remaining_time":0.5486541279},
{"learn":[4.204659106],"iteration":385,"passed_time":0.3439945406,"remaining_time":0.5471830258},
{"learn":[4.202968852],"iteration":386,"passed_time":0.3445053801,"remaining_time":0.5456894006},
{"learn":[4.197261935],"iteration":387,"passed_time":0.3450232342,"remaining_time":0.5442119055},
{"learn":[4.196934403],"iteration":388,"passed_time":0.3455302057,"remaining_time":0.5427222511},
{"learn":[4.192479929],"iteration":389,"passed_time":0.3460564271,"remaining_time":0.5412677449},
{"learn":[4.190243116],"iteration":390,"passed_time":0.3465714553,"remaining_time":0.5398005531},
{"learn":[4.185852431],"iteration":391,"passed_time":0.3470952516,"remaining_time":0.5383518189},
{"learn":[4.180967944],"iteration":392,"passed_time":0.3476306921,"remaining_time":0.5369257764},
{"learn":[4.178283162],"iteration":393,"passed_time":0.3481475842,"remaining_time":0.535475726},
{"learn":[4.176341157],"iteration":394,"passed_time":0.3486571911,"remaining_time":0.5340192421},
{"learn":[4.176041504],"iteration":395,"passed_time":0.3491552742,"remaining_time":0.5325499637},
{"learn":[4.175564513],"iteration":396,"passed_time":0.349660973,"remaining_time":0.5310971454},
{"learn":[4.170830274],"iteration":397,"passed_time":0.3501803101,"remaining_time":0.5296697153},
{"learn":[4.167804808],"iteration":398,"passed_time":0.3507189974,"remaining_time":0.5282759836},
{"learn":[4.165860548],"iteration":399,"passed_time":0.351258817,"remaining_time":0.5268882255},
{"learn":[4.160950571],"iteration":400,"passed_time":0.3517785149,"remaining_time":0.5254746394},
{"learn":[4.158544115],"iteration":401,"passed_time":0.3522934328,"remaining_time":0.5240583901},
{"learn":[4.154448767],"iteration":402,"passed_time":0.3528294445,"remaining_time":0.522677862},
{"learn":[4.15197457],"iteration":403,"passed_time":0.3533454648,"remaining_time":0.5212720223},
{"learn":[4.149562679],"iteration":404,"passed_time":0.3538509832,"remaining_time":0.5198551482},
{"learn":[4.149327961],"iteration":405,"passed_time":0.3543408292,"remaining_time":0.5184198339},
{"learn":[4.147444889],"iteration":406,"passed_time":0.3548439828,"remaining_time":0.5170085547},
{"learn":[4.147254809],"iteration":407,"passed_time":0.3553227658,"remaining_time":0.515566366},
{"learn":[4.144589165],"iteration":408,"passed_time":0.3558524644,"remaining_time":0.5142024608},
{"learn":[4.141691034],"iteration":409,"passed_time":0.3563772127,"remaining_time":0.5128355012},
{"learn":[4.138893468],"iteration":410,"passed_time":0.356886028,"remaining_time":0.5114498066},
{"learn":[4.136964597],"iteration":411,"passed_time":0.3573965168,"remaining_time":0.510070757},
{"learn":[4.133773523],"iteration":412,"passed_time":0.3579240409,"remaining_time":0.5087201259},
{"learn":[4.131363444],"iteration":413,"passed_time":0.3584441196,"remaining_time":0.5073629325},
{"learn":[4.130228592],"iteration":414,"passed_time":0.3589435855,"remaining_time":0.5059807169},
{"learn":[4.12884186],"iteration":415,"passed_time":0.3594783045,"remaining_time":0.5046522352},
{"learn":[4.12413494],"iteration":416,"passed_time":0.3600139154,"remaining_time":0.5033288073},
{"learn":[4.119422508],"iteration":417,"passed_time":0.36053688,"remaining_time":0.5019915411},
{"learn":[4.117038244],"iteration":418,"passed_time":0.3610486515,"remaining_time":0.5006426408},
{"learn":[4.116067631],"iteration":419,"passed_time":0.3615412531,"remaining_time":0.4992712543},
{"learn":[4.110343455],"iteration":420,"passed_time":0.3620637668,"remaining_time":0.4979451805},
{"learn":[4.105604544],"iteration":421,"passed_time":0.3625848576,"remaining_time":0.4966209661},
{"learn":[4.103390131],"iteration":422,"passed_time":0.3630976812,"remaining_time":0.495289272},
{"learn":[4.096724402],"iteration":423,"passed_time":0.3636046026,"remaining_time":0.4939534224},
{"learn":[4.093431279],"iteration":424,"passed_time":0.3656706021,"remaining_time":0.4947308146},
{"learn":[4.091412744],"iteration":425,"passed_time":0.3663687856,"remaining_time":0.4936518379},
{"learn":[4.091192901],"iteration":426,"passed_time":0.3669597443,"remaining_time":0.4924307576},
{"learn":[4.088994581],"iteration":427,"passed_time":0.3675237942,"remaining_time":0.4911766595},
{"learn":[4.087845355],"iteration":428,"passed_time":0.3680994781,"remaining_time":0.4899412634},
{"learn":[4.083650279],"iteration":429,"passed_time":0.3687024487,"remaining_time":0.4887451064},
{"learn":[4.079840652],"iteration":430,"passed_time":0.3692846262,"remaining_time":0.4875242513},
{"learn":[4.075707828],"iteration":431,"passed_time":0.3698567728,"remaining_time":0.4862931643},
{"learn":[4.071345409],"iteration":432,"passed_time":0.3704172653,"remaining_time":0.4850498601},
{"learn":[4.067460475],"iteration":433,"passed_time":0.3709751223,"remaining_time":0.4838062655},
{"learn":[4.064914749],"iteration":434,"passed_time":0.3715214755,"remaining_time":0.4825508819},
{"learn":[4.063823175],"iteration":435,"passed_time":0.3720850443,"remaining_time":0.4813210207},
{"learn":[4.058898471],"iteration":436,"passed_time":0.3726559235,"remaining_time":0.4801036269},
{"learn":[4.054120355],"iteration":437,"passed_time":0.3733007974,"remaining_time":0.4789841281},
{"learn":[4.052715901],"iteration":438,"passed_time":0.3738266981,"remaining_time":0.4777147554},
{"learn":[4.052114167],"iteration":439,"passed_time":0.3743285991,"remaining_time":0.476418217},
{"learn":[4.051377267],"iteration":440,"passed_time":0.37484013,"remaining_time":0.475137489},
{"learn":[4.049275336],"iteration":441,"passed_time":0.3753732557,"remaining_time":0.4738875038},
{"learn":[4.047099198],"iteration":442,"passed_time":0.3758696953,"remaining_time":0.4725946282},
{"learn":[4.044348685],"iteration":443,"passed_time":0.3764039634,"remaining_time":0.471352711},
{"learn":[4.042822379],"iteration":444,"passed_time":0.3769313372,"remaining_time":0.4701053756},
{"learn":[4.041258611],"iteration":445,"passed_time":0.3774554142,"remaining_time":0.4688571737},
{"learn":[4.040044254],"iteration":446,"passed_time":0.3779955044,"remaining_time":0.4676320222},
{"learn":[4.036860137],"iteration":447,"passed_time":0.3785443026,"remaining_time":0.4664206585},
{"learn":[4.036372284],"iteration":448,"passed_time":0.3790630785,"remaining_time":0.4651754037},
{"learn":[4.03368231],"iteration":449,"passed_time":0.3795813935,"remaining_time":0.4639328143},
{"learn":[4.032439519],"iteration":450,"passed_time":0.3800921328,"remaining_time":0.4626842149},
{"learn":[4.032008634],"iteration":451,"passed_time":0.3806151877,"remaining_time":0.4614538116},
{"learn":[4.030034932],"iteration":452,"passed_time":0.3811305666,"remaining_time":0.4602172625},
{"learn":[4.028173412],"iteration":453,"passed_time":0.38163846,"remaining_time":0.458974888},
{"learn":[4.023806097],"iteration":454,"passed_time":0.3821749928,"remaining_time":0.4577700463},
{"learn":[4.020239186],"iteration":455,"passed_time":0.3827122771,"remaining_time":0.4565690323},
{"learn":[4.017384838],"iteration":456,"passed_time":0.3832231567,"remaining_time":0.4553395494},
{"learn":[4.016468229],"iteration":457,"passed_time":0.3837459109,"remaining_time":0.454127257},
{"learn":[4.014530169],"iteration":458,"passed_time":0.3842823936,"remaining_time":0.4529341502},
{"learn":[4.012884822],"iteration":459,"passed_time":0.3848066008,"remaining_time":0.4517294879},
{"learn":[4.008924707],"iteration":460,"passed_time":0.3853278419,"remaining_time":0.4505243097},
{"learn":[4.008286778],"iteration":461,"passed_time":0.3858436817,"remaining_time":0.4493158025},
{"learn":[4.006444202],"iteration":462,"passed_time":0.3863711457,"remaining_time":0.4481237694},
{"learn":[4.003284363],"iteration":463,"passed_time":0.386887196,"remaining_time":0.4469214161},
{"learn":[3.999811484],"iteration":464,"passed_time":0.387407896,"remaining_time":0.4457273642},
{"learn":[3.997483319],"iteration":465,"passed_time":0.3879285158,"remaining_time":0.4445361103},
{"learn":[3.99708333],"iteration":466,"passed_time":0.3884345553,"remaining_time":0.4433310877},
{"learn":[3.995860263],"iteration":467,"passed_time":0.388953702,"remaining_time":0.4421439519},
{"learn":[3.994131111],"iteration":468,"passed_time":0.3894756345,"remaining_time":0.4409628186},
{"learn":[3.993125499],"iteration":469,"passed_time":0.389990332,"remaining_time":0.4397763319},
{"learn":[3.992954084],"iteration":470,"passed_time":0.3905084166,"remaining_time":0.4385965018},
{"learn":[3.990635743],"iteration":471,"passed_time":0.391033706,"remaining_time":0.4374275356},
{"learn":[3.986678254],"iteration":472,"passed_time":0.3915551475,"remaining_time":0.4362570037},
{"learn":[3.986393291],"iteration":473,"passed_time":0.3920421075,"remaining_time":0.4350509463},
{"learn":[3.986152671],"iteration":474,"passed_time":0.392553438,"remaining_time":0.4338748525},
{"learn":[3.985596662],"iteration":475,"passed_time":0.3930539361,"remaining_time":0.4326896271},
{"learn":[3.983853457],"iteration":476,"passed_time":0.3935713993,"remaining_time":0.4315258739},
{"learn":[3.983263928],"iteration":477,"passed_time":0.394089113,"remaining_time":0.4303650983},
{"learn":[3.980067202],"iteration":478,"passed_time":0.3946159156,"remaining_time":0.4292168936},
{"learn":[3.978115407],"iteration":479,"passed_time":0.3951378081,"remaining_time":0.4280659587},
{"learn":[3.972661644],"iteration":480,"passed_time":0.3956532972,"remaining_time":0.4269107303},
{"learn":[3.969938254],"iteration":481,"passed_time":0.396168636,"remaining_time":0.4257579948},
{"learn":[3.968211434],"iteration":482,"passed_time":0.3966826421,"remaining_time":0.424606472},
{"learn":[3.966113368],"iteration":483,"passed_time":0.3972001053,"remaining_time":0.4234612693},
{"learn":[3.962246044],"iteration":484,"passed_time":0.3977260562,"remaining_time":0.4223276679},
{"learn":[3.961319703],"iteration":485,"passed_time":0.39825825,"remaining_time":0.4212031697},
{"learn":[3.96078191],"iteration":486,"passed_time":0.3987570545,"remaining_time":0.4200459322},
{"learn":[3.958913633],"iteration":487,"passed_time":0.399277073,"remaining_time":0.4189136504},
{"learn":[3.957428286],"iteration":488,"passed_time":0.3998020018,"remaining_time":0.4177890039},
{"learn":[3.952641965],"iteration":489,"passed_time":0.4003215092,"remaining_time":0.4166611627},
{"learn":[3.951486786],"iteration":490,"passed_time":0.4008395737,"remaining_time":0.4155343035},
{"learn":[3.94938344],"iteration":491,"passed_time":0.4013682302,"remaining_time":0.4144208556},
{"learn":[3.947297924],"iteration":492,"passed_time":0.4019048832,"remaining_time":0.4133180036},
{"learn":[3.946284886],"iteration":493,"passed_time":0.402422617,"remaining_time":0.4121980652},
{"learn":[3.943288204],"iteration":494,"passed_time":0.4029904748,"remaining_time":0.4111316965},
{"learn":[3.943076488],"iteration":495,"passed_time":0.4035183496,"remaining_time":0.4100267101},
{"learn":[3.942347078],"iteration":496,"passed_time":0.4040248601,"remaining_time":0.4089024238},
{"learn":[3.940251541],"iteration":497,"passed_time":0.4045385455,"remaining_time":0.4077878511},
{"learn":[3.939011019],"iteration":498,"passed_time":0.40505659,"remaining_time":0.4066800633},
{"learn":[3.938760512],"iteration":499,"passed_time":0.4055485303,"remaining_time":0.4055485303},
{"learn":[3.934522727],"iteration":500,"passed_time":0.4060609831,"remaining_time":0.4044399812},
{"learn":[3.930091193],"iteration":501,"passed_time":0.4066421321,"remaining_time":0.4034019557},
{"learn":[3.927671752],"iteration":502,"passed_time":0.4072094788,"remaining_time":0.4023521092},
{"learn":[3.927280041],"iteration":503,"passed_time":0.4077442579,"remaining_time":0.4012721268},
{"learn":[3.925987561],"iteration":504,"passed_time":0.4082633646,"remaining_time":0.4001789415},
{"learn":[3.921645957],"iteration":505,"passed_time":0.4087972218,"remaining_time":0.399102426},
{"learn":[3.920333743],"iteration":506,"passed_time":0.4092991228,"remaining_time":0.3979969774},
{"learn":[3.918659461],"iteration":507,"passed_time":0.4098116959,"remaining_time":0.3969042409},
{"learn":[3.916124385],"iteration":508,"passed_time":0.4103371757,"remaining_time":0.3958262343},
{"learn":[3.913849268],"iteration":509,"passed_time":0.4108580059,"remaining_time":0.3947459273},
{"learn":[3.912826119],"iteration":510,"passed_time":0.4113810307,"remaining_time":0.39366991},
{"learn":[3.910034145],"iteration":511,"passed_time":0.4119006384,"remaining_time":0.392592796},
{"learn":[3.90792379],"iteration":512,"passed_time":0.412479529,"remaining_time":0.3915741338},
{"learn":[3.907823851],"iteration":513,"passed_time":0.4129830433,"remaining_time":0.3904859126},
{"learn":[3.904527401],"iteration":514,"passed_time":0.4134969793,"remaining_time":0.3894097766},
{"learn":[3.903378283],"iteration":515,"passed_time":0.4140229902,"remaining_time":0.3883471459},
{"learn":[3.902170135],"iteration":516,"passed_time":0.414527717,"remaining_time":0.3872667066},
{"learn":[3.899435429],"iteration":517,"passed_time":0.4150407812,"remaining_time":0.3861962481},
{"learn":[3.897497505],"iteration":518,"passed_time":0.4155628439,"remaining_time":0.3851362773},
{"learn":[3.896426119],"iteration":519,"passed_time":0.416083103,"remaining_time":0.3840767104},
{"learn":[3.896044669],"iteration":520,"passed_time":0.4166362302,"remaining_time":0.3830494323},
{"learn":[3.892795942],"iteration":521,"passed_time":0.4171860305,"remaining_time":0.3820209245},
{"learn":[3.892413888],"iteration":522,"passed_time":0.4177250785,"remaining_time":0.3809844406},
{"learn":[3.891738985],"iteration":523,"passed_time":0.4182679644,"remaining_time":0.3799533417},
{"learn":[3.88822057],"iteration":524,"passed_time":0.4188543606,"remaining_time":0.3789634692},
{"learn":[3.883837053],"iteration":525,"passed_time":0.4193975172,"remaining_time":0.3779361657},
{"learn":[3.881769742],"iteration":526,"passed_time":0.419911904,"remaining_time":0.3768848778},
{"learn":[3.880356898],"iteration":527,"passed_time":0.4204363718,"remaining_time":0.3758446354},
{"learn":[3.879250273],"iteration":528,"passed_time":0.4210047506,"remaining_time":0.3748454396},
{"learn":[3.877174493],"iteration":529,"passed_time":0.42152516,"remaining_time":0.3738053305},
{"learn":[3.875854201],"iteration":530,"passed_time":0.422037693,"remaining_time":0.3727602222},
{"learn":[3.873189396],"iteration":531,"passed_time":0.4225601766,"remaining_time":0.3717258697},
{"learn":[3.871583368],"iteration":532,"passed_time":0.4230797843,"remaining_time":0.370690918},
{"learn":[3.869622679],"iteration":533,"passed_time":0.4235867658,"remaining_time":0.369646878},
{"learn":[3.866860164],"iteration":534,"passed_time":0.4241093797,"remaining_time":0.3686184329},
{"learn":[3.864498444],"iteration":535,"passed_time":0.4246224839,"remaining_time":0.3675836428},
{"learn":[3.861416322],"iteration":536,"passed_time":0.4251463104,"remaining_time":0.3665600404},
{"learn":[3.860265769],"iteration":537,"passed_time":0.4256390523,"remaining_time":0.3655116026},
{"learn":[3.859328725],"iteration":538,"passed_time":0.4261555736,"remaining_time":0.3644855648},
{"learn":[3.858521278],"iteration":539,"passed_time":0.4266638277,"remaining_time":0.3634543718},
{"learn":[3.85599111],"iteration":540,"passed_time":0.4271848884,"remaining_time":0.3624359774},
{"learn":[3.852379816],"iteration":541,"passed_time":0.4277200985,"remaining_time":0.3614313747},
{"learn":[3.851327537],"iteration":542,"passed_time":0.4282504785,"remaining_time":0.3604244359},
{"learn":[3.847854898],"iteration":543,"passed_time":0.4287717897,"remaining_time":0.3594116473},
{"learn":[3.847083414],"iteration":544,"passed_time":0.4292750635,"remaining_time":0.3583856035},
{"learn":[3.845397429],"iteration":545,"passed_time":0.4298035396,"remaining_time":0.3573824304},
{"learn":[3.841933528],"iteration":546,"passed_time":0.430333118,"remaining_time":0.3563819058},
{"learn":[3.840996474],"iteration":547,"passed_time":0.4308568342,"remaining_time":0.3553782647},
{"learn":[3.838355966],"iteration":548,"passed_time":0.431392886,"remaining_time":0.3543865056},
{"learn":[3.83342799],"iteration":549,"passed_time":0.431930972,"remaining_time":0.353398068},
{"learn":[3.828161535],"iteration":550,"passed_time":0.4324488661,"remaining_time":0.352394811},
{"learn":[3.823502399],"iteration":551,"passed_time":0.4329589541,"remaining_time":0.3513869772},
{"learn":[3.820068862],"iteration":552,"passed_time":0.4335113598,"remaining_time":0.3504151498},
{"learn":[3.817951642],"iteration":553,"passed_time":0.4341202775,"remaining_time":0.3494903317},
{"learn":[3.815785958],"iteration":554,"passed_time":0.4347173459,"remaining_time":0.3485571512},
{"learn":[3.81503012],"iteration":555,"passed_time":0.4353249998,"remaining_time":0.3476336329},
{"learn":[3.813529315],"iteration":556,"passed_time":0.4359285033,"remaining_time":0.3467079479},
{"learn":[3.808881326],"iteration":557,"passed_time":0.4391276266,"remaining_time":0.3478394461},
{"learn":[3.808740434],"iteration":558,"passed_time":0.4397783763,"remaining_time":0.346945016},
{"learn":[3.80714352],"iteration":559,"passed_time":0.4404326432,"remaining_time":0.3460542197},
{"learn":[3.80573346],"iteration":560,"passed_time":0.4410801662,"remaining_time":0.3451589892},
{"learn":[3.803370052],"iteration":561,"passed_time":0.4417169569,"remaining_time":0.344256276},
{"learn":[3.803215211],"iteration":562,"passed_time":0.4423656423,"remaining_time":0.3433637401},
{"learn":[3.801309667],"iteration":563,"passed_time":0.4429955588,"remaining_time":0.3424575596},
{"learn":[3.800003847],"iteration":564,"passed_time":0.4436352355,"remaining_time":0.3415598716},
{"learn":[3.798026138],"iteration":565,"passed_time":0.444290316,"remaining_time":0.3406749066},
{"learn":[3.794745847],"iteration":566,"passed_time":0.444923399,"remaining_time":0.3397739538},
{"learn":[3.794312041],"iteration":567,"passed_time":0.4455433548,"remaining_time":0.33886396},
{"learn":[3.792205926],"iteration":568,"passed_time":0.4461878515,"remaining_time":0.3379735747},
{"learn":[3.788991061],"iteration":569,"passed_time":0.4468961406,"remaining_time":0.3371321762},
{"learn":[3.787391572],"iteration":570,"passed_time":0.4475571816,"remaining_time":0.3362557459},
{"learn":[3.7826445],"iteration":571,"passed_time":0.4482216798,"remaining_time":0.3353826555},
{"learn":[3.781700331],"iteration":572,"passed_time":0.4488703251,"remaining_time":0.3344984796},
{"learn":[3.780045374],"iteration":573,"passed_time":0.4494886174,"remaining_time":0.3335925976},
{"learn":[3.775462644],"iteration":574,"passed_time":0.4501368619,"remaining_time":0.3327098545},
{"learn":[3.773711943],"iteration":575,"passed_time":0.4508136939,"remaining_time":0.3318489691},
{"learn":[3.772415806],"iteration":576,"passed_time":0.4514540119,"remaining_time":0.3309619533},
{"learn":[3.770170875],"iteration":577,"passed_time":0.4521049119,"remaining_time":0.330083517},
{"learn":[3.765166479],"iteration":578,"passed_time":0.452777178,"remaining_time":0.3292214023},
{"learn":[3.763976102],"iteration":579,"passed_time":0.4534608159,"remaining_time":0.328368177},
{"learn":[3.760761708],"iteration":580,"passed_time":0.4541183697,"remaining_time":0.3274967245},
{"learn":[3.758155662],"iteration":581,"passed_time":0.4547628764,"remaining_time":0.3266166363},
{"learn":[3.756844548],"iteration":582,"passed_time":0.4554113815,"remaining_time":0.3257402162},
{"learn":[3.753098923],"iteration":583,"passed_time":0.4560550765,"remaining_time":0.3248611504},
{"learn":[3.751618946],"iteration":584,"passed_time":0.4566632579,"remaining_time":0.3239576958},
{"learn":[3.751398464],"iteration":585,"passed_time":0.4572496441,"remaining_time":0.3230398509},
{"learn":[3.749920103],"iteration":586,"passed_time":0.4578946819,"remaining_time":0.3221644014},
{"learn":[3.748237465],"iteration":587,"passed_time":0.4585516946,"remaining_time":0.3212981261},
{"learn":[3.746021536],"iteration":588,"passed_time":0.4591686041,"remaining_time":0.3204045777},
{"learn":[3.74417648],"iteration":589,"passed_time":0.4597993322,"remaining_time":0.3195215698},
{"learn":[3.738788389],"iteration":590,"passed_time":0.4603711181,"remaining_time":0.3185986249},
{"learn":[3.736021611],"iteration":591,"passed_time":0.4609403788,"remaining_time":0.3176751259},
{"learn":[3.734546151],"iteration":592,"passed_time":0.4615184377,"remaining_time":0.3167588603},
{"learn":[3.733527479],"iteration":593,"passed_time":0.4620722463,"remaining_time":0.3158271583},
{"learn":[3.733026392],"iteration":594,"passed_time":0.4626249627,"remaining_time":0.314895983},
{"learn":[3.730314752],"iteration":595,"passed_time":0.4632146156,"remaining_time":0.3139911153},
{"learn":[3.727342596],"iteration":596,"passed_time":0.4637815515,"remaining_time":0.3130719686},
{"learn":[3.725459604],"iteration":597,"passed_time":0.4643204792,"remaining_time":0.3121351717},
{"learn":[3.723158842],"iteration":598,"passed_time":0.4648520116,"remaining_time":0.3111947524},
{"learn":[3.722362756],"iteration":599,"passed_time":0.4653779024,"remaining_time":0.3102519349},
{"learn":[3.721443615],"iteration":600,"passed_time":0.4659049455,"remaining_time":0.30931127},
{"learn":[3.720743486],"iteration":601,"passed_time":0.4664473504,"remaining_time":0.3083821353},
{"learn":[3.720215334],"iteration":602,"passed_time":0.4669831918,"remaining_time":0.3074499621},
{"learn":[3.719436563],"iteration":603,"passed_time":0.4675193137,"remaining_time":0.3065192852},
{"learn":[3.715046574],"iteration":604,"passed_time":0.4680467877,"remaining_time":0.3055842664},
{"learn":[3.71443396],"iteration":605,"passed_time":0.4685942131,"remaining_time":0.3046635643},
{"learn":[3.712938941],"iteration":606,"passed_time":0.4692594674,"remaining_time":0.3038203801},
{"learn":[3.712814764],"iteration":607,"passed_time":0.4699358302,"remaining_time":0.3029849432},
{"learn":[3.71235348],"iteration":608,"passed_time":0.470610525,"remaining_time":0.3021489578},
{"learn":[3.711223749],"iteration":609,"passed_time":0.4712138162,"remaining_time":0.3012678497},
{"learn":[3.710755648],"iteration":610,"passed_time":0.4718318581,"remaining_time":0.3003970422},
{"learn":[3.708668039],"iteration":611,"passed_time":0.4725685761,"remaining_time":0.2996022999},
{"learn":[3.705623591],"iteration":612,"passed_time":0.4731698932,"remaining_time":0.2987222654},
{"learn":[3.704045802],"iteration":613,"passed_time":0.4737880653,"remaining_time":0.2978537349},
{"learn":[3.699915209],"iteration":614,"passed_time":0.4743457319,"remaining_time":0.2969481411},
{"learn":[3.696182221],"iteration":615,"passed_time":0.4748845595,"remaining_time":0.2960319332},
{"learn":[3.694263278],"iteration":616,"passed_time":0.4754095684,"remaining_time":0.2951083706},
{"learn":[3.693810229],"iteration":617,"passed_time":0.4759392169,"remaining_time":0.2941889658},
{"learn":[3.690900932],"iteration":618,"passed_time":0.4765684219,"remaining_time":0.2933320981},
{"learn":[3.688020895],"iteration":619,"passed_time":0.4771519221,"remaining_time":0.2924479522},
{"learn":[3.685491894],"iteration":620,"passed_time":0.4777375868,"remaining_time":0.2915660956},
{"learn":[3.684328128],"iteration":621,"passed_time":0.4782822865,"remaining_time":0.2906602963},
{"learn":[3.680640153],"iteration":622,"passed_time":0.4788347724,"remaining_time":0.2897603679},
{"learn":[3.678932783],"iteration":623,"passed_time":0.4793778788,"remaining_time":0.2888559013},
{"learn":[3.674167041],"iteration":624,"passed_time":0.4798906323,"remaining_time":0.2879343794},
{"learn":[3.672200976],"iteration":625,"passed_time":0.480412194,"remaining_time":0.2870194258},
{"learn":[3.670606604],"iteration":626,"passed_time":0.4809349582,"remaining_time":0.2861064425},
{"learn":[3.665506042],"iteration":627,"passed_time":0.4814522611,"remaining_time":0.2851914668},
{"learn":[3.664214007],"iteration":628,"passed_time":0.4819965801,"remaining_time":0.2842936903},
{"learn":[3.66261643],"iteration":629,"passed_time":0.4825106763,"remaining_time":0.2833792861},
{"learn":[3.662118449],"iteration":630,"passed_time":0.4830255642,"remaining_time":0.2824666136},
{"learn":[3.660871366],"iteration":631,"passed_time":0.4835380672,"remaining_time":0.2815538113},
{"learn":[3.656695243],"iteration":632,"passed_time":0.4840554903,"remaining_time":0.2806451263},
{"learn":[3.654497801],"iteration":633,"passed_time":0.4845994685,"remaining_time":0.2797530055},
{"learn":[3.654189134],"iteration":634,"passed_time":0.485127624,"remaining_time":0.2788528862},
{"learn":[3.653957699],"iteration":635,"passed_time":0.4856371307,"remaining_time":0.2779432635},
{"learn":[3.651920725],"iteration":636,"passed_time":0.4861614982,"remaining_time":0.2770433656},
{"learn":[3.65106705],"iteration":637,"passed_time":0.4866847635,"remaining_time":0.2761440194},
{"learn":[3.650612844],"iteration":638,"passed_time":0.4871970059,"remaining_time":0.2752396231},
{"learn":[3.649884732],"iteration":639,"passed_time":0.4877092884,"remaining_time":0.2743364747},
{"learn":[3.646276182],"iteration":640,"passed_time":0.4882543389,"remaining_time":0.2734528981},
{"learn":[3.645808194],"iteration":641,"passed_time":0.4887532336,"remaining_time":0.272544638},
{"learn":[3.645042989],"iteration":642,"passed_time":0.4892693641,"remaining_time":0.2716472208},
{"learn":[3.639864499],"iteration":643,"passed_time":0.4898114784,"remaining_time":0.2707653514},
{"learn":[3.637318478],"iteration":644,"passed_time":0.4904027047,"remaining_time":0.2699115661},
{"learn":[3.636344905],"iteration":645,"passed_time":0.4909350788,"remaining_time":0.2690263435},
{"learn":[3.634754643],"iteration":646,"passed_time":0.4914428219,"remaining_time":0.268128773},
{"learn":[3.630724975],"iteration":647,"passed_time":0.4919572087,"remaining_time":0.2672360146},
{"learn":[3.629408252],"iteration":648,"passed_time":0.4924767363,"remaining_time":0.2663472025},
{"learn":[3.62790646],"iteration":649,"passed_time":0.4930050019,"remaining_time":0.2654642318},
{"learn":[3.627388973],"iteration":650,"passed_time":0.4935338888,"remaining_time":0.2645826839},
{"learn":[3.625163557],"iteration":651,"passed_time":0.494037824,"remaining_time":0.2636888999},
{"learn":[3.623701985],"iteration":652,"passed_time":0.4945638851,"remaining_time":0.2628080676},
{"learn":[3.622342639],"iteration":653,"passed_time":0.4950897558,"remaining_time":0.2619282194},
{"learn":[3.621130639],"iteration":654,"passed_time":0.495601938,"remaining_time":0.2610422422},
{"learn":[3.619125665],"iteration":655,"passed_time":0.4961290012,"remaining_time":0.2601652079},
{"learn":[3.618878783],"iteration":656,"passed_time":0.496627475,"remaining_time":0.2592743135},
{"learn":[3.616207429],"iteration":657,"passed_time":0.4971528447,"remaining_time":0.258398591},
{"learn":[3.61206486],"iteration":658,"passed_time":0.4976638144,"remaining_time":0.2575164806},
{"learn":[3.611955873],"iteration":659,"passed_time":0.4981752051,"remaining_time":0.2566357117},
{"learn":[3.610713743],"iteration":660,"passed_time":0.4987013363,"remaining_time":0.2557636203},
{"learn":[3.610044025],"iteration":661,"passed_time":0.4992169758,"remaining_time":0.2548872172},
{"learn":[3.607342669],"iteration":662,"passed_time":0.4997328156,"remaining_time":0.2540120043},
{"learn":[3.602510618],"iteration":663,"passed_time":0.5002497377,"remaining_time":0.2531384215},
{"learn":[3.600492392],"iteration":664,"passed_time":0.5008007606,"remaining_time":0.2522830899},
{"learn":[3.597171065],"iteration":665,"passed_time":0.5013116402,"remaining_time":0.2514085403},
{"learn":[3.594358798],"iteration":666,"passed_time":0.5018340336,"remaining_time":0.2505408294},
{"learn":[3.593945251],"iteration":667,"passed_time":0.5023480898,"remaining_time":0.2496700087},
{"learn":[3.593607748],"iteration":668,"passed_time":0.502864561,"remaining_time":0.2488014494},
{"learn":[3.592238714],"iteration":669,"passed_time":0.503386243,"remaining_time":0.2479365077},
{"learn":[3.590144654],"iteration":670,"passed_time":0.5039177253,"remaining_time":0.2470773944},
{"learn":[3.587151536],"iteration":671,"passed_time":0.5044473237,"remaining_time":0.2462183366},
{"learn":[3.586070865],"iteration":672,"passed_time":0.5049653581,"remaining_time":0.2453546391},
{"learn":[3.585102746],"iteration":673,"passed_time":0.5054934935,"remaining_time":0.2444968529},
{"learn":[3.584362847],"iteration":674,"passed_time":0.5060054553,"remaining_time":0.2436322563},
{"learn":[3.581407561],"iteration":675,"passed_time":0.5065270671,"remaining_time":0.242773328},
{"learn":[3.57919422],"iteration":676,"passed_time":0.507051565,"remaining_time":0.2419167732},
{"learn":[3.577632204],"iteration":677,"passed_time":0.5075855324,"remaining_time":0.2410656953},
{"learn":[3.573911195],"iteration":678,"passed_time":0.5081032662,"remaining_time":0.240207877},
{"learn":[3.573408216],"iteration":679,"passed_time":0.5086087947,"remaining_time":0.2393453152},
{"learn":[3.571076482],"iteration":680,"passed_time":0.5091216384,"remaining_time":0.2384872285},
{"learn":[3.568177107],"iteration":681,"passed_time":0.5096636024,"remaining_time":0.2376437325},
{"learn":[3.564824621],"iteration":682,"passed_time":0.5101892125,"remaining_time":0.2367935291},
{"learn":[3.562475026],"iteration":683,"passed_time":0.5107076278,"remaining_time":0.2359409508},
{"learn":[3.561226889],"iteration":684,"passed_time":0.5112392203,"remaining_time":0.2350954079},
{"learn":[3.559383467],"iteration":685,"passed_time":0.51175979,"remaining_time":0.2342457348},
{"learn":[3.555209766],"iteration":686,"passed_time":0.5122767822,"remaining_time":0.2333953899},
{"learn":[3.55345383],"iteration":687,"passed_time":0.512790658,"remaining_time":0.2325446007},
{"learn":[3.552300968],"iteration":688,"passed_time":0.5133058967,"remaining_time":0.2316954047},
{"learn":[3.551253986],"iteration":689,"passed_time":0.5138232797,"remaining_time":0.2308481402},
{"learn":[3.549807725],"iteration":690,"passed_time":0.5143386987,"remaining_time":0.2300009521},
{"learn":[3.547992926],"iteration":691,"passed_time":0.514873047,"remaining_time":0.2291631481},
{"learn":[3.545438607],"iteration":692,"passed_time":0.5153974847,"remaining_time":0.2283218294},
{"learn":[3.543313763],"iteration":693,"passed_time":0.5159265019,"remaining_time":0.2274834432},
{"learn":[3.542962896],"iteration":694,"passed_time":0.5164479835,"remaining_time":0.2266426402},
{"learn":[3.539800465],"iteration":695,"passed_time":0.5169797764,"remaining_time":0.2258072587},
{"learn":[3.53953187],"iteration":696,"passed_time":0.5174873291,"remaining_time":0.2249622105},
{"learn":[3.536332425],"iteration":697,"passed_time":0.5180505472,"remaining_time":0.2241422138},
{"learn":[3.534993327],"iteration":698,"passed_time":0.5185669483,"remaining_time":0.2233027917},
{"learn":[3.531637011],"iteration":699,"passed_time":0.5190934502,"remaining_time":0.2224686215},
{"learn":[3.531040284],"iteration":700,"passed_time":0.519591864,"remaining_time":0.2216233485},
{"learn":[3.529973872],"iteration":701,"passed_time":0.5201291483,"remaining_time":0.2207955644},
{"learn":[3.527325183],"iteration":702,"passed_time":0.5206578649,"remaining_time":0.219964987},
{"learn":[3.527200815],"iteration":703,"passed_time":0.5211538736,"remaining_time":0.219121515},
{"learn":[3.523459911],"iteration":704,"passed_time":0.5216764475,"remaining_time":0.2182901447},
{"learn":[3.522729934],"iteration":705,"passed_time":0.5221984301,"remaining_time":0.2174594029},
{"learn":[3.522260582],"iteration":706,"passed_time":0.5227220461,"remaining_time":0.2166302115},
{"learn":[3.518641591],"iteration":707,"passed_time":0.5232463335,"remaining_time":0.2158021601},
{"learn":[3.516856405],"iteration":708,"passed_time":0.5237823552,"remaining_time":0.2149797819},
{"learn":[3.515083413],"iteration":709,"passed_time":0.5242996781,"remaining_time":0.2141505728},
{"learn":[3.514671214],"iteration":710,"passed_time":0.5248170011,"remaining_time":0.2133222409},
{"learn":[3.512617621],"iteration":711,"passed_time":0.5253339432,"remaining_time":0.2124946287},
{"learn":[3.510747971],"iteration":712,"passed_time":0.5258708869,"remaining_time":0.211675939},
{"learn":[3.508149266],"iteration":713,"passed_time":0.5263881196,"remaining_time":0.2108501432},
{"learn":[3.504557165],"iteration":714,"passed_time":0.526897927,"remaining_time":0.2100222506},
{"learn":[3.501367208],"iteration":715,"passed_time":0.5274168432,"remaining_time":0.2091988596},
{"learn":[3.497593362],"iteration":716,"passed_time":0.5279440467,"remaining_time":0.2083795889},
{"learn":[3.496291169],"iteration":717,"passed_time":0.5284698773,"remaining_time":0.2075605925},
{"learn":[3.49330374],"iteration":718,"passed_time":0.5290042656,"remaining_time":0.2067457561},
{"learn":[3.490044385],"iteration":719,"passed_time":0.529530467,"remaining_time":0.2059285149},
{"learn":[3.488891789],"iteration":720,"passed_time":0.5300407954,"remaining_time":0.2051059389},
{"learn":[3.486869081],"iteration":721,"passed_time":0.5305478571,"remaining_time":0.2042829699},
{"learn":[3.486303638],"iteration":722,"passed_time":0.5310778162,"remaining_time":0.2034696474},
{"learn":[3.486035862],"iteration":723,"passed_time":0.5316421366,"remaining_time":0.2026702068},
{"learn":[3.482668951],"iteration":724,"passed_time":0.5322456083,"remaining_time":0.2018862652},
{"learn":[3.47820549],"iteration":725,"passed_time":0.5327902178,"remaining_time":0.2010806056},
{"learn":[3.474392283],"iteration":726,"passed_time":0.5333181828,"remaining_time":0.2002694139},
{"learn":[3.472268163],"iteration":727,"passed_time":0.5338368085,"remaining_time":0.1994555109},
{"learn":[3.471209164],"iteration":728,"passed_time":0.5343713872,"remaining_time":0.1986483483},
{"learn":[3.470049971],"iteration":729,"passed_time":0.5349030098,"remaining_time":0.1978408392},
{"learn":[3.469078654],"iteration":730,"passed_time":0.5354347426,"remaining_time":0.1970341255},
{"learn":[3.468643292],"iteration":731,"passed_time":0.5359608338,"remaining_time":0.1962260976},
{"learn":[3.468134848],"iteration":732,"passed_time":0.5364635364,"remaining_time":0.1954103195},
{"learn":[3.467820182],"iteration":733,"passed_time":0.5369582023,"remaining_time":0.194592482},
{"learn":[3.465776156],"iteration":734,"passed_time":0.5374805257,"remaining_time":0.1937854956},
{"learn":[3.463037608],"iteration":735,"passed_time":0.5380435033,"remaining_time":0.1929938653},
{"learn":[3.45965637],"iteration":736,"passed_time":0.5385725205,"remaining_time":0.1921907366},
{"learn":[3.457275091],"iteration":737,"passed_time":0.5390995135,"remaining_time":0.1913876322},
{"learn":[3.455522955],"iteration":738,"passed_time":0.539622889,"remaining_time":0.1905839973},
{"learn":[3.451270508],"iteration":739,"passed_time":0.5401421961,"remaining_time":0.1897796905},
{"learn":[3.450978947],"iteration":740,"passed_time":0.540658537,"remaining_time":0.1889751162},
{"learn":[3.450608492],"iteration":741,"passed_time":0.5411523211,"remaining_time":0.1881634755},
{"learn":[3.448122004],"iteration":742,"passed_time":0.5417233554,"remaining_time":0.187379411},
{"learn":[3.445646714],"iteration":743,"passed_time":0.5422649788,"remaining_time":0.1865857991},
{"learn":[3.44411263],"iteration":744,"passed_time":0.5427938156,"remaining_time":0.1857884872},
{"learn":[3.443264164],"iteration":745,"passed_time":0.5433144554,"remaining_time":0.1849891041},
{"learn":[3.439521363],"iteration":746,"passed_time":0.5438304456,"remaining_time":0.1841888926},
{"learn":[3.436809225],"iteration":747,"passed_time":0.5443598536,"remaining_time":0.1833939614},
{"learn":[3.435509465],"iteration":748,"passed_time":0.5448895122,"remaining_time":0.1825998232},
{"learn":[3.434450277],"iteration":749,"passed_time":0.5454302737,"remaining_time":0.1818100912},
{"learn":[3.431786753],"iteration":750,"passed_time":0.5459700432,"remaining_time":0.1810206934},
{"learn":[3.430150302],"iteration":751,"passed_time":0.5464865344,"remaining_time":0.1802242826},
{"learn":[3.42696281],"iteration":752,"passed_time":0.5470242898,"remaining_time":0.1794355904},
{"learn":[3.426870334],"iteration":753,"passed_time":0.5475193165,"remaining_time":0.1786336231},
{"learn":[3.425200309],"iteration":754,"passed_time":0.5480427421,"remaining_time":0.1778416845},
{"learn":[3.423383783],"iteration":755,"passed_time":0.5485738336,"remaining_time":0.1770529304},
{"learn":[3.422752979],"iteration":756,"passed_time":0.5490803641,"remaining_time":0.1762569729},
{"learn":[3.420845924],"iteration":757,"passed_time":0.5496064152,"remaining_time":0.1754680112},
{"learn":[3.418917862],"iteration":758,"passed_time":0.5501319552,"remaining_time":0.17467958},
{"learn":[3.417095735],"iteration":759,"passed_time":0.5506565231,"remaining_time":0.1738915336},
{"learn":[3.414391848],"iteration":760,"passed_time":0.5511909115,"remaining_time":0.1731072639},
{"learn":[3.41426711],"iteration":761,"passed_time":0.5516866597,"remaining_time":0.1723115814},
{"learn":[3.411976013],"iteration":762,"passed_time":0.5522075199,"remaining_time":0.1715244852},
{"learn":[3.408614844],"iteration":763,"passed_time":0.5527401547,"remaining_time":0.1707417232},
{"learn":[3.407906721],"iteration":764,"passed_time":0.5532559144,"remaining_time":0.1699544312},
{"learn":[3.407494015],"iteration":765,"passed_time":0.5537788089,"remaining_time":0.1691700278},
{"learn":[3.406287128],"iteration":766,"passed_time":0.5543050804,"remaining_time":0.1683873321},
{"learn":[3.404600442],"iteration":767,"passed_time":0.5548191065,"remaining_time":0.1676016051},
{"learn":[3.404012662],"iteration":768,"passed_time":0.5553210275,"remaining_time":0.1668129484},
{"learn":[3.400398762],"iteration":769,"passed_time":0.5558423487,"remaining_time":0.1660308314},
{"learn":[3.399737714],"iteration":770,"passed_time":0.5563357921,"remaining_time":0.1652411108},
{"learn":[3.399185251],"iteration":771,"passed_time":0.5568494074,"remaining_time":0.1644581151},
{"learn":[3.397245411],"iteration":772,"passed_time":0.5573772722,"remaining_time":0.163680001},
{"learn":[3.396229831],"iteration":773,"passed_time":0.5578787322,"remaining_time":0.1628948236},
{"learn":[3.394002836],"iteration":774,"passed_time":0.5583936602,"remaining_time":0.1621142884},
{"learn":[3.389617243],"iteration":775,"passed_time":0.5589149614,"remaining_time":0.1613362775},
{"learn":[3.385426488],"iteration":776,"passed_time":0.5594893928,"remaining_time":0.1605741758},
{"learn":[3.385072258],"iteration":777,"passed_time":0.5600067759,"remaining_time":0.1597962779},
{"learn":[3.383842366],"iteration":778,"passed_time":0.5605384887,"remaining_time":0.1590231142},
{"learn":[3.380110746],"iteration":779,"passed_time":0.5610832686,"remaining_time":0.1582542552},
{"learn":[3.378595218],"iteration":780,"passed_time":0.5615951602,"remaining_time":0.1574767479},
{"learn":[3.377371219],"iteration":781,"passed_time":0.5621067914,"remaining_time":0.1566998472},
{"learn":[3.375814782],"iteration":782,"passed_time":0.5626261586,"remaining_time":0.1559257681},
{"learn":[3.374195887],"iteration":783,"passed_time":0.5631399742,"remaining_time":0.1551508092},
{"learn":[3.373704309],"iteration":784,"passed_time":0.5636719175,"remaining_time":0.1543814806},
{"learn":[3.372971757],"iteration":785,"passed_time":0.5641964755,"remaining_time":0.1536107452},
{"learn":[3.371565136],"iteration":786,"passed_time":0.5647215144,"remaining_time":0.1528407657},
{"learn":[3.3700309],"iteration":787,"passed_time":0.5652487679,"remaining_time":0.1520720036},
{"learn":[3.368186663],"iteration":788,"passed_time":0.5657695581,"remaining_time":0.1513021252},
{"learn":[3.366710398],"iteration":789,"passed_time":0.5662925027,"remaining_time":0.1505334501},
{"learn":[3.364598042],"iteration":790,"passed_time":0.5668074006,"remaining_time":0.1497632702},
{"learn":[3.36348442],"iteration":791,"passed_time":0.5673298742,"remaining_time":0.1489957245},
{"learn":[3.362001759],"iteration":792,"passed_time":0.5678410344,"remaining_time":0.1482258438},
{"learn":[3.361580401],"iteration":793,"passed_time":0.5683636784,"remaining_time":0.1474595941},
{"learn":[3.359543675],"iteration":794,"passed_time":0.5688796786,"remaining_time":0.1466922442},
{"learn":[3.35766119],"iteration":795,"passed_time":0.5694122832,"remaining_time":0.1459297811},
{"learn":[3.354592969],"iteration":796,"passed_time":0.569954618,"remaining_time":0.1451703732},
{"learn":[3.350985986],"iteration":797,"passed_time":0.5704848778,"remaining_time":0.1444084528},
{"learn":[3.349589624],"iteration":798,"passed_time":0.5710120412,"remaining_time":0.1436463333},
{"learn":[3.349110856],"iteration":799,"passed_time":0.5715499067,"remaining_time":0.1428874767},
{"learn":[3.345315441],"iteration":800,"passed_time":0.5720685123,"remaining_time":0.142124387},
{"learn":[3.34397474],"iteration":801,"passed_time":0.5725876089,"remaining_time":0.1413620281},
{"learn":[3.343800902],"iteration":802,"passed_time":0.5730945303,"remaining_time":0.1405972883},
{"learn":[3.342329465],"iteration":803,"passed_time":0.5736776297,"remaining_time":0.1398517605},
{"learn":[3.34220347],"iteration":804,"passed_time":0.5741871965,"remaining_time":0.139088824},
{"learn":[3.341279219],"iteration":805,"passed_time":0.5747010924,"remaining_time":0.1383275582},
{"learn":[3.337329521],"iteration":806,"passed_time":0.5752406114,"remaining_time":0.1375730334},
{"learn":[3.336708453],"iteration":807,"passed_time":0.5757617422,"remaining_time":0.1368146714},
{"learn":[3.333252703],"iteration":808,"passed_time":0.5762796063,"remaining_time":0.1360561246},
{"learn":[3.332186769],"iteration":809,"passed_time":0.5768031722,"remaining_time":0.1352995095},
{"learn":[3.330594851],"iteration":810,"passed_time":0.5773216375,"remaining_time":0.1345422805},
{"learn":[3.327867442],"iteration":811,"passed_time":0.5778420468,"remaining_time":0.1337860897},
{"learn":[3.327563111],"iteration":812,"passed_time":0.5783586783,"remaining_time":0.1330296099},
{"learn":[3.326308994],"iteration":813,"passed_time":0.5788993197,"remaining_time":0.1322792057},
{"learn":[3.326249879],"iteration":814,"passed_time":0.57939609,"remaining_time":0.1315193578},
{"learn":[3.322336238],"iteration":815,"passed_time":0.5799305384,"remaining_time":0.1307686508},
{"learn":[3.320491154],"iteration":816,"passed_time":0.5804702177,"remaining_time":0.1300196449},
{"learn":[3.320434271],"iteration":817,"passed_time":0.580957328,"remaining_time":0.1292594544},
{"learn":[3.319609638],"iteration":818,"passed_time":0.5814657225,"remaining_time":0.1285046346},
{"learn":[3.316182682],"iteration":819,"passed_time":0.581988637,"remaining_time":0.1277536032},
{"learn":[3.313126612],"iteration":820,"passed_time":0.5825188266,"remaining_time":0.1270047137},
{"learn":[3.311222803],"iteration":821,"passed_time":0.5830489862,"remaining_time":0.1262563498},
{"learn":[3.309627335],"iteration":822,"passed_time":0.583572492,"remaining_time":0.1255070852},
{"learn":[3.307974895],"iteration":823,"passed_time":0.5840998357,"remaining_time":0.1247591882},
{"learn":[3.307321505],"iteration":824,"passed_time":0.58460817,"remaining_time":0.1240077936},
{"learn":[3.306759087],"iteration":825,"passed_time":0.5851283388,"remaining_time":0.1232594806},
{"learn":[3.30484037],"iteration":826,"passed_time":0.5856403107,"remaining_time":0.1225100045},
{"learn":[3.30201994],"iteration":827,"passed_time":0.5861908726,"remaining_time":0.1217691185},
{"learn":[3.299302297],"iteration":828,"passed_time":0.5867177052,"remaining_time":0.1210237969},
{"learn":[3.298132671],"iteration":829,"passed_time":0.587932052,"remaining_time":0.1204198179},
{"learn":[3.296976183],"iteration":830,"passed_time":0.5886348408,"remaining_time":0.1197103347},
{"learn":[3.293144745],"iteration":831,"passed_time":0.5892324704,"remaining_time":0.1189796334},
{"learn":[3.290284404],"iteration":832,"passed_time":0.5898573464,"remaining_time":0.1182547141},
{"learn":[3.288285745],"iteration":833,"passed_time":0.5905387684,"remaining_time":0.1175412896},
{"learn":[3.286662667],"iteration":834,"passed_time":0.5912263257,"remaining_time":0.1168291542},
{"learn":[3.285692682],"iteration":835,"passed_time":0.5919006743,"remaining_time":0.1161144863},
{"learn":[3.284565611],"iteration":836,"passed_time":0.5925024724,"remaining_time":0.1153857862},
{"learn":[3.283897383],"iteration":837,"passed_time":0.5931314157,"remaining_time":0.1146626364},
{"learn":[3.280712855],"iteration":838,"passed_time":0.5937810242,"remaining_time":0.1139436769},
{"learn":[3.280468341],"iteration":839,"passed_time":0.5943170259,"remaining_time":0.113203243},
{"learn":[3.277814895],"iteration":840,"passed_time":0.5948647419,"remaining_time":0.1124655101},
{"learn":[3.276316385],"iteration":841,"passed_time":0.5953967553,"remaining_time":0.1117252819},
{"learn":[3.27557063],"iteration":842,"passed_time":0.5959315144,"remaining_time":0.110986059},
{"learn":[3.27499628],"iteration":843,"passed_time":0.5964426245,"remaining_time":0.1102429495},
{"learn":[3.273569958],"iteration":844,"passed_time":0.5969946995,"remaining_time":0.1095079035},
{"learn":[3.269665595],"iteration":845,"passed_time":0.5975362928,"remaining_time":0.1087713819},
{"learn":[3.267984685],"iteration":846,"passed_time":0.5980786276,"remaining_time":0.1080354546},
{"learn":[3.267702508],"iteration":847,"passed_time":0.5985819214,"remaining_time":0.1072929859},
{"learn":[3.266671924],"iteration":848,"passed_time":0.5991175724,"remaining_time":0.1065568356},
{"learn":[3.265359825],"iteration":849,"passed_time":0.5996489946,"remaining_time":0.1058204108},
{"learn":[3.2618983],"iteration":850,"passed_time":0.600163171,"remaining_time":0.1050814483},
{"learn":[3.260456253],"iteration":851,"passed_time":0.6007505793,"remaining_time":0.1043557344},
{"learn":[3.258389147],"iteration":852,"passed_time":0.6012899981,"remaining_time":0.1036220747},
{"learn":[3.258108469],"iteration":853,"passed_time":0.6018118705,"remaining_time":0.1028858701},
{"learn":[3.256424936],"iteration":854,"passed_time":0.6023594862,"remaining_time":0.1021545328},
{"learn":[3.254817983],"iteration":855,"passed_time":0.6028987246,"remaining_time":0.1014222154},
{"learn":[3.253898449],"iteration":856,"passed_time":0.6034371413,"remaining_time":0.1006902114},
{"learn":[3.253023652],"iteration":857,"passed_time":0.603958653,"remaining_time":0.09995586098},
{"learn":[3.252845542],"iteration":858,"passed_time":0.6044744026,"remaining_time":0.09922106027},
{"learn":[3.252316026],"iteration":859,"passed_time":0.6049888697,"remaining_time":0.09848656018},
{"learn":[3.24975301],"iteration":860,"passed_time":0.605514119,"remaining_time":0.0977543119},
{"learn":[3.249151075],"iteration":861,"passed_time":0.6060524155,"remaining_time":0.09702463264},
{"learn":[3.246257135],"iteration":862,"passed_time":0.6065893792,"remaining_time":0.09629518534},
{"learn":[3.243826471],"iteration":863,"passed_time":0.6071086862,"remaining_time":0.09556340431},
{"learn":[3.243190653],"iteration":864,"passed_time":0.6076409802,"remaining_time":0.09483414142},
{"learn":[3.24008797],"iteration":865,"passed_time":0.6081621111,"remaining_time":0.0941036061},
{"learn":[3.240036811],"iteration":866,"passed_time":0.6086723393,"remaining_time":0.09337188135},
{"learn":[3.238676314],"iteration":867,"passed_time":0.6091994225,"remaining_time":0.09264323015},
{"learn":[3.237848782],"iteration":868,"passed_time":0.6097329891,"remaining_time":0.09191602023},
{"learn":[3.236405498],"iteration":869,"passed_time":0.6102650025,"remaining_time":0.09118902337},
{"learn":[3.233378068],"iteration":870,"passed_time":0.6107862837,"remaining_time":0.09046088473},
{"learn":[3.233169169],"iteration":871,"passed_time":0.6113011014,"remaining_time":0.08973227177},
{"learn":[3.232434885],"iteration":872,"passed_time":0.611817272,"remaining_time":0.08900434541},
{"learn":[3.229978115],"iteration":873,"passed_time":0.6123658097,"remaining_time":0.08828156982},
{"learn":[3.229648848],"iteration":874,"passed_time":0.6128860286,"remaining_time":0.08755514695},
{"learn":[3.227208761],"iteration":875,"passed_time":0.6134102659,"remaining_time":0.08682976367},
{"learn":[3.226258869],"iteration":876,"passed_time":0.6139297534,"remaining_time":0.08610417293},
{"learn":[3.225331995],"iteration":877,"passed_time":0.6144785516,"remaining_time":0.08538312448},
{"learn":[3.221968268],"iteration":878,"passed_time":0.6150889476,"remaining_time":0.08467094728},
{"learn":[3.221166317],"iteration":879,"passed_time":0.6156143372,"remaining_time":0.08394740962},
{"learn":[3.220047503],"iteration":880,"passed_time":0.6161314197,"remaining_time":0.08322319971},
{"learn":[3.21982781],"iteration":881,"passed_time":0.6166521196,"remaining_time":0.08249994344},
{"learn":[3.216693405],"iteration":882,"passed_time":0.6171804855,"remaining_time":0.08177816172},
{"learn":[3.214798761],"iteration":883,"passed_time":0.6177214675,"remaining_time":0.08105847311},
{"learn":[3.214395085],"iteration":884,"passed_time":0.6182413959,"remaining_time":0.08033645257},
{"learn":[3.213470696],"iteration":885,"passed_time":0.6187540291,"remaining_time":0.07961394956},
{"learn":[3.211595017],"iteration":886,"passed_time":0.6192768033,"remaining_time":0.0788932117},
{"learn":[3.210965255],"iteration":887,"passed_time":0.6198058806,"remaining_time":0.07817371468},
{"learn":[3.209413583],"iteration":888,"passed_time":0.6203594187,"remaining_time":0.0774577002},
{"learn":[3.208331683],"iteration":889,"passed_time":0.6209095397,"remaining_time":0.0767416285},
{"learn":[3.207110711],"iteration":890,"passed_time":0.6214453109,"remaining_time":0.07602417383},
{"learn":[3.204519413],"iteration":891,"passed_time":0.6219909926,"remaining_time":0.07530832646},
{"learn":[3.201421296],"iteration":892,"passed_time":0.6225113619,"remaining_time":0.07458982724},
{"learn":[3.200691259],"iteration":893,"passed_time":0.6230411006,"remaining_time":0.07387288217},
{"learn":[3.200485067],"iteration":894,"passed_time":0.6235601772,"remaining_time":0.07315510459},
{"learn":[3.197467568],"iteration":895,"passed_time":0.6240809673,"remaining_time":0.07243796942},
{"learn":[3.195838544],"iteration":896,"passed_time":0.624604433,"remaining_time":0.07172157926},
{"learn":[3.195671746],"iteration":897,"passed_time":0.6251037787,"remaining_time":0.07100287909},
{"learn":[3.194213094],"iteration":898,"passed_time":0.6256416542,"remaining_time":0.07028899564},
{"learn":[3.192884691],"iteration":899,"passed_time":0.62614104,"remaining_time":0.06957122666},
{"learn":[3.188364239],"iteration":900,"passed_time":0.6266616497,"remaining_time":0.0688562745},
{"learn":[3.185219478],"iteration":901,"passed_time":0.6271893943,"remaining_time":0.06814252843},
{"learn":[3.184120387],"iteration":902,"passed_time":0.6277047031,"remaining_time":0.06742785847},
{"learn":[3.183725321],"iteration":903,"passed_time":0.628304095,"remaining_time":0.06672255876},
{"learn":[3.181264554],"iteration":904,"passed_time":0.6288327415,"remaining_time":0.06601006678},
{"learn":[3.180741589],"iteration":905,"passed_time":0.6293554556,"remaining_time":0.06529736515},
{"learn":[3.179782639],"iteration":906,"passed_time":0.6298693715,"remaining_time":0.06458418031},
{"learn":[3.176377564],"iteration":907,"passed_time":0.6303970659,"remaining_time":0.06387283047},
{"learn":[3.174078182],"iteration":908,"passed_time":0.6309596928,"remaining_time":0.06316538179},
{"learn":[3.171242379],"iteration":909,"passed_time":0.6314797715,"remaining_time":0.06245404333},
{"learn":[3.170421012],"iteration":910,"passed_time":0.6319926151,"remaining_time":0.06174241794},
{"learn":[3.170087224],"iteration":911,"passed_time":0.6325297091,"remaining_time":0.06103356842},
{"learn":[3.167303059],"iteration":912,"passed_time":0.6330416709,"remaining_time":0.0603227003},
{"learn":[3.16705966],"iteration":913,"passed_time":0.6335415377,"remaining_time":0.05961112936},
{"learn":[3.165667683],"iteration":914,"passed_time":0.6340555738,"remaining_time":0.05890133746},
{"learn":[3.164689733],"iteration":915,"passed_time":0.6345813743,"remaining_time":0.05819305179},
{"learn":[3.163311455],"iteration":916,"passed_time":0.6350997294,"remaining_time":0.05748449023},
{"learn":[3.159425016],"iteration":917,"passed_time":0.6356193371,"remaining_time":0.05677645495},
{"learn":[3.159327058],"iteration":918,"passed_time":0.6361402675,"remaining_time":0.05606894632},
{"learn":[3.15819426],"iteration":919,"passed_time":0.6366668697,"remaining_time":0.0553623365},
{"learn":[3.157086603],"iteration":920,"passed_time":0.6371831605,"remaining_time":0.05465523309},
{"learn":[3.153354154],"iteration":921,"passed_time":0.6377242227,"remaining_time":0.05395063923},
{"learn":[3.153261317],"iteration":922,"passed_time":0.638233028,"remaining_time":0.05324370873},
{"learn":[3.153168454],"iteration":923,"passed_time":0.6387409915,"remaining_time":0.05253713783},
{"learn":[3.152080399],"iteration":924,"passed_time":0.6392687461,"remaining_time":0.05183260103},
{"learn":[3.151635144],"iteration":925,"passed_time":0.6398009599,"remaining_time":0.05112880241},
{"learn":[3.147762655],"iteration":926,"passed_time":0.6403378735,"remaining_time":0.05042574408},
{"learn":[3.147172317],"iteration":927,"passed_time":0.6408593551,"remaining_time":0.04972184651},
{"learn":[3.146254125],"iteration":928,"passed_time":0.6414000164,"remaining_time":0.0490198075},
{"learn":[3.144869828],"iteration":929,"passed_time":0.6419101845,"remaining_time":0.04831582034},
{"learn":[3.143466218],"iteration":930,"passed_time":0.6424684223,"remaining_time":0.04761581218},
{"learn":[3.141919643],"iteration":931,"passed_time":0.6429855549,"remaining_time":0.04691310915},
{"learn":[3.141054135],"iteration":932,"passed_time":0.6435051124,"remaining_time":0.04621097806},
{"learn":[3.139390417],"iteration":933,"passed_time":0.6440350916,"remaining_time":0.04550997436},
{"learn":[3.139025283],"iteration":934,"passed_time":0.644538145,"remaining_time":0.04480746463},
{"learn":[3.137824183],"iteration":935,"passed_time":0.6450588449,"remaining_time":0.04410658769},
{"learn":[3.135620453],"iteration":936,"passed_time":0.6455875816,"remaining_time":0.04340663569},
{"learn":[3.13443178],"iteration":937,"passed_time":0.6461079809,"remaining_time":0.04270649767},
{"learn":[3.132765713],"iteration":938,"passed_time":0.6466399542,"remaining_time":0.04200749436},
{"learn":[3.131434124],"iteration":939,"passed_time":0.6471717873,"remaining_time":0.04130883748},
{"learn":[3.128384262],"iteration":940,"passed_time":0.6476865148,"remaining_time":0.04060946267},
{"learn":[3.128120455],"iteration":941,"passed_time":0.648199629,"remaining_time":0.03991038056},
{"learn":[3.126314615],"iteration":942,"passed_time":0.648732394,"remaining_time":0.03921288066},
{"learn":[3.125409666],"iteration":943,"passed_time":0.6492533946,"remaining_time":0.03851503188},
{"learn":[3.123072589],"iteration":944,"passed_time":0.6497764895,"remaining_time":0.03781767928},
{"learn":[3.122921099],"iteration":945,"passed_time":0.6503002558,"remaining_time":0.03712073342},
{"learn":[3.122182662],"iteration":946,"passed_time":0.6508097325,"remaining_time":0.03642335356},
{"learn":[3.120040951],"iteration":947,"passed_time":0.6513309134,"remaining_time":0.03572701213},
{"learn":[3.118767799],"iteration":948,"passed_time":0.6518460619,"remaining_time":0.03503071565},
{"learn":[3.118203218],"iteration":949,"passed_time":0.6523849996,"remaining_time":0.03433605261},
{"learn":[3.116343362],"iteration":950,"passed_time":0.6529248894,"remaining_time":0.03364176612},
{"learn":[3.11480829],"iteration":951,"passed_time":0.6534522131,"remaining_time":0.03294717041},
{"learn":[3.112607903],"iteration":952,"passed_time":0.6539880043,"remaining_time":0.03225334334},
{"learn":[3.111661241],"iteration":953,"passed_time":0.6545058083,"remaining_time":0.03155898027},
{"learn":[3.110249676],"iteration":954,"passed_time":0.655035076,"remaining_time":0.03086552714},
{"learn":[3.107333579],"iteration":955,"passed_time":0.6555749858,"remaining_time":0.0301729073},
{"learn":[3.107149851],"iteration":956,"passed_time":0.6560625971,"remaining_time":0.02947825671},
{"learn":[3.106867336],"iteration":957,"passed_time":0.6566473411,"remaining_time":0.02878829679},
{"learn":[3.10364681],"iteration":958,"passed_time":0.6572941626,"remaining_time":0.02810121029},
{"learn":[3.102703811],"iteration":959,"passed_time":0.6578537733,"remaining_time":0.02741057389},
{"learn":[3.101469264],"iteration":960,"passed_time":0.6584489878,"remaining_time":0.02672165507},
{"learn":[3.09863569],"iteration":961,"passed_time":0.6590446031,"remaining_time":0.0260329469},
{"learn":[3.09645939],"iteration":962,"passed_time":0.6596265801,"remaining_time":0.02534390806},
{"learn":[3.096240186],"iteration":963,"passed_time":0.6601799278,"remaining_time":0.0246540222},
{"learn":[3.094838828],"iteration":964,"passed_time":0.6607654322,"remaining_time":0.02396558562},
{"learn":[3.094176802],"iteration":965,"passed_time":0.6613510768,"remaining_time":0.02327736709},
{"learn":[3.093182279],"iteration":966,"passed_time":0.6618652833,"remaining_time":0.0225869228},
{"learn":[3.090150687],"iteration":967,"passed_time":0.6623994111,"remaining_time":0.02189750119},
{"learn":[3.088612829],"iteration":968,"passed_time":0.6629429484,"remaining_time":0.02120870114},
{"learn":[3.087153684],"iteration":969,"passed_time":0.6634865659,"remaining_time":0.02052020307},
{"learn":[3.085866843],"iteration":970,"passed_time":0.6640379094,"remaining_time":0.01983223416},
{"learn":[3.082669094],"iteration":971,"passed_time":0.6645781098,"remaining_time":0.01914422538},
{"learn":[3.081047548],"iteration":972,"passed_time":0.6651007437,"remaining_time":0.01845603297},
{"learn":[3.079684322],"iteration":973,"passed_time":0.6656520672,"remaining_time":0.01776894635},
{"learn":[3.07613431],"iteration":974,"passed_time":0.6662155158,"remaining_time":0.01708244912},
{"learn":[3.074005935],"iteration":975,"passed_time":0.6667466474,"remaining_time":0.01639540936},
{"learn":[3.072988853],"iteration":976,"passed_time":0.6672711653,"remaining_time":0.01570853306},
{"learn":[3.072344268],"iteration":977,"passed_time":0.6677784374,"remaining_time":0.01502160084},
{"learn":[3.070654438],"iteration":978,"passed_time":0.6683131263,"remaining_time":0.01433562375},
{"learn":[3.069724506],"iteration":979,"passed_time":0.6688372734,"remaining_time":0.01364974027},
{"learn":[3.067763166],"iteration":980,"passed_time":0.6693679942,"remaining_time":0.01296431385},
{"learn":[3.066737893],"iteration":981,"passed_time":0.6699374753,"remaining_time":0.01227991299},
{"learn":[3.065248174],"iteration":982,"passed_time":0.6704699597,"remaining_time":0.01159510612},
{"learn":[3.063186837],"iteration":983,"passed_time":0.6710211028,"remaining_time":0.01091091224},
{"learn":[3.062880371],"iteration":984,"passed_time":0.6715295273,"remaining_time":0.01022633798},
{"learn":[3.061288645],"iteration":985,"passed_time":0.6720450966,"remaining_time":0.009542222466},
{"learn":[3.059970575],"iteration":986,"passed_time":0.6725812686,"remaining_time":0.00885871985},
{"learn":[3.059576341],"iteration":987,"passed_time":0.673083861,"remaining_time":0.008175107623},
{"learn":[3.058175919],"iteration":988,"passed_time":0.6736317974,"remaining_time":0.007492365796},
{"learn":[3.056830702],"iteration":989,"passed_time":0.6741607645,"remaining_time":0.006809704692},
{"learn":[3.056336579],"iteration":990,"passed_time":0.6746656417,"remaining_time":0.00612713499},
{"learn":[3.055810414],"iteration":991,"passed_time":0.6751939975,"remaining_time":0.005445112883},
{"learn":[3.055476518],"iteration":992,"passed_time":0.6756936338,"remaining_time":0.004763197821},
{"learn":[3.053331734],"iteration":993,"passed_time":0.676233303,"remaining_time":0.004081891165},
{"learn":[3.050890374],"iteration":994,"passed_time":0.6767462168,"remaining_time":0.003400734758},
{"learn":[3.04972623],"iteration":995,"passed_time":0.6772895738,"remaining_time":0.002720038449},
{"learn":[3.047217327],"iteration":996,"passed_time":0.6778137209,"remaining_time":0.002039559842},
{"learn":[3.047155483],"iteration":997,"passed_time":0.6783170147,"remaining_time":0.001359352735},
{"learn":[3.04430671],"iteration":998,"passed_time":0.6788573755,"remaining_time":0.0006795369124},
{"learn":[3.042664195],"iteration":999,"passed_time":0.6793775644,"remaining_time":0}
]}